Workbook

Sheet Read Me
A1: IPC Digital Platform — Estimate v2
A2: Rebuilt 18 Aug 2026 against verified evidence from the live IPC estate. Supersedes v1.
B4: WHAT CHANGED IN v2
B5: 1. Verified, not assumed | C5: v1 assumed ~2,500 pages of migration and a greenfield build. Both were wrong. The live estate was inspected and the baselines below are counted, not estimated.
B6: 2. Probabilistic, not point | C6: v1 gave a single number plus a 12% contingency I chose. v2 derives P50 / P80 / P90 from the three-point spread already in the model, and derives contingency from an expected-value risk register.
B7: 3. Build-vs-adopt tested | C7: v1 priced three flavours of bespoke build. v2 adds Scenario D, which tests replatforming the existing estate against a full rebuild.
B8: 4. Unit economics | C8: v2 computes cost per transaction against the real catalogue and order volumes, which is the first number an evaluation committee will calculate.
B9: 5. Price, not just cost | C9: v2 adds margin, GST, milestone billing, cash-flow curve, performance guarantee and liquidated-damages exposure.
B10: 6. Triangulated | C10: v2 cross-checks the bottom-up build against a top-down analogy and a capability-count method. Where they disagree, that gap is stated rather than hidden.
B12: VERIFIED BASELINES | C12: All figures below were read from the live IPC estate on 18 Aug 2026.
B13: Current CMS | C13: Joomla. Confirmed from the meta-generator on every page. Migration is Joomla-to-target, not greenfield.
B14: Current commerce | C14: OpenCart, live at /shop/. Confirmed from URL routing (index.php?route=product/category). Doc B's e-commerce module is a REPLATFORM with existing product, customer and order data — scope absent from Doc B entirely.
B15: IPRS catalogue | C15: 702 reference substances. Counted from List-of-IP-Reference-Substances.pdf, last updated 24/06/2026. Each row carries current lot, one previous lot with validity, and quantity per vial.
B16: IMPRS catalogue | C16: 639 reference impurities. Counted from Impuritie_List.pdf, last updated 24/06/2026. Each row carries API/monograph linkage, lot data, quantity and TWO price tiers.
B17: Total priced SKUs | C17: 1,341 plus publications, subscriptions, phytochemical and botanical standards, and the Prednisone calibrator tablet.
... B24: Estate hygiene | C24: Production pages link to a vendor staging host (ipc.maxtraserver.in); a G20 banner from 2023 is still live; the site map's own last-updated date is July 2019; the NFI section still headlines 2021 while NFI 2026 is being procured. This is direct evidence for Doc B's archival and lifecycle requirements.
B26: VERIFIED COMPLIANCE POSITION
B27: GIGW 3.0 | C27: 88 mandatory guidelines across quality, accessibility, cybersecurity and lifecycle management. Conforms to WCAG 2.1 Level AA with 17 added success criteria. Its cybersecurity chapter was written by CERT-In and EXPLICITLY covers mobile apps — so Doc A omitting GIGW is a compliance gap, not merely an inconsistency with Doc B.
B28: STQC | C28: Conformity is evidenced by Certified Quality Website (CQW) certification from the STQC Directorate, involving document review plus frontend and backend testing.
B29: DPDP | C29: Both documents cite the 'DPDP Bill, 2023'. It has been an Act since August 2023, and the DPDP Rules were notified on 13 November 2025. Compliance is phased: the Board and definitions took effect immediately, penalties and Consent Manager registration from 13 November 2026, and FULL COMPLIANCE IS DUE 13 MAY 2027. A 16-month programme starting now lands on or after that date — DPDP is a hard delivery constraint, not a design preference.
B30: Correction to v1 | C30: v1 argued Google Analytics conflicts with DPDP on localisation grounds. That was wrong: the final Rules use a blacklist model for cross-border transfer, not data localisation. The real constraints are consent, purpose limitation, retention limits and a 90-day grievance timeline.
B32: HOW TO USE | C32: Blue = input, change these. Black = formula. Green = cross-sheet link. Yellow = primary lever.
B33: Row shading | C33: Pink = scope the documents omit but the outcome requires. Green = scope newly identified from inspecting the live estate, absent from both documents.
B34: Excluded | C34: IPC staff time; content authoring; payment gateway TDR; statutory fees; physical cold-chain infrastructure; IPC-side hardware.
B36: WHAT CHANGED IN v5
B37: One sheet, both scenarios | C37: This workbook now prices two different questions in one place: what it costs to build Lotmark as a product, and what IPC costs under five routes including adopting that product.
B38: Product Build sheet | C38: New. The product had never been estimated — only customer deployments had. Same three-point and Monte Carlo method.
B39: Scenario E | C39: New. Every IPC module carries a factor for what survives once the product supplies the core, modelled per module rather than as a global multiplier.
B40: Why it matters | C40: Scenarios A to D all assume a bespoke build. If the product exists, none of them is the cheapest route for IPC, and the workbook previously could not say so.
B42: UNITS AND CONVENTIONS
B43: PD — person-day | C43: One person working one day. 21 person-days make one person-month. All effort figures in this workbook are person-days unless a column header says otherwise.
B44: INR crore (Cr) | C44: Ten million rupees. Used for build cost, total cost of ownership and quoted price.
B45: INR lakh | C45: One hundred thousand rupees. Used for pass-through and licence lines. Note that crore and lakh both appear in this workbook — always read the column header.
B46: INR / PD | C46: The blended rate: rupees per person-day. Multiply effort by this to get cost.
B47: Factor (0–1) | C47: Dimensionless. The fraction of a module that survives under a given scenario. 1.00 means untouched; 0.15 means 15% of the original effort remains.
B48: Probability (0–1) | C48: Dimensionless likelihood of a risk event, used to weight its impact.
B49: P50 / P80 / P90 | C49: Confidence levels from the Monte Carlo, expressed in person-days. P80 means four runs in five finish at or below that figure.
B50: Sigma | C50: Standard deviation of a module's three-point spread, in person-days.
B51: FP / KSLOC | C51: Function points and thousands of source lines of code, used only on the Independent Estimate sheet.
B52: Months | C52: Schedule durations on the Timeline sheet. Columns M1 to M16 are programme months, not calendar months.
B53: FTE | C53: Full-time equivalent people, derived as person-days in a month divided by 21.
B54: Counts | C54: Orders, SKUs, records and clause tallies are plain counts and carry no monetary or effort unit.
B55: Where a unit is ambiguous | C55: Column headers now carry the unit in brackets, and headline figures carry it inside the cell format so a copied cell keeps its unit.

Sheet Build & Verification
A1: Build and Verification
A2: Three deliverables, one toolchain. The toolchain is carried inside the product and exportable from its Build screen.
B4: THE THREE DELIVERABLES
A5: Ref | B5: Outcome | C5: File | D5: What it is
A6: D1 | B6: Product | C6: lotmark-app.html | D6: The working application. Nine roles, 22 console modules, ISO 17034 and 21 CFR Part 11 controls that can be exercised rather than read. Carries build.py inside it, exportable from Build and verification.
A7: D2 | B7: Wireframe | C7: lotmark-product-wireframe.html | D7: 37 screens of product design, including the market and deployment decision screens. Its screen list is the source the product's coverage map is generated from.
A8: D3 | B8: Estimation | C8: Lotmark_and_IPC_Estimate_v5.xlsx | D8: This workbook. Cost and revenue for both the product build and five IPC routes, in one place.
B10: SHIP SEQUENCE — run in this order after any change
A11: Step | B11: Command | C11: Guards | D11: Why it is in this position
A12: 1 | B12: recalc the workbook | C12: cached values must exist | D12: openpyxl drops cached values on save; every reference check would otherwise report a false failure
A13: 2 | B13: python3 build.py sync | C13: asserts substitution size and key symbols; refuses to write a damaged file | D13: regenerates the coverage map from the wireframe and injects figures, so drift cannot survive a build
A14: 3 | B14: python3 build.py check | C14: 23 checks; exits non-zero | D14: catches duplicate declarations, broken references, undefined permissions, coverage drift
A15: 4 | B15: open the product, Build and verification | C15: 16 runtime invariants | D15: only evaluable with data loaded — signatures, chain, referential integrity
A16: 5 | B16: the five JS harnesses | C16: 166 assertions, each asserting its own count | D16: behaviour, not structure
B18: WHAT THE TOOLCHAIN CHECKS, AND THE DEFECT THAT PUT IT THERE
A19: Ref | B19: Check | C19: Where it runs | D19: The defect it exists because of
A20: V1 | B20: Duplicate function and constant declarations | C20: build.py check | D20: A re-run patch script inserted a block twice, nested inside the first. JavaScript accepts it silently.
A21: V2 | B21: Cross-sheet references land on numeric cells | C21: build.py check | D21: A hardcoded coordinate pointed at a paragraph of prose after rows shifted.
A22: V3 | B22: Named ranges resolve to numbers | C22: build.py check | D22: Same root cause: coordinates as an addressing scheme.
A23: V4 | B23: No cached formula errors | C23: build.py check | D23: A row insert broke an entire block, because openpyxl does not translate formulas.
A24: V5 | B24: Every permission used is defined and granted | C24: build.py check + product | D24: An export guarded on a permission absent from the model, so it refused everyone silently.
A25: V6 | B25: Every module has a renderer | C25: build.py check + product | D25: A dead fallback key crashed the app for a role with no console modules.
A26: V7 | B26: Inline handlers call functions that exist | C26: build.py check | D26: Handlers are strings; a rename does not break them until someone clicks.
A27: V8 | B27: No backticks or mangled escapes in handlers | C27: build.py check | D27: A nested backtick and a Python-mangled apostrophe each terminated a template literal.
A28: V9 | B28: Coverage map matches the wireframe | C28: build.py check | D28: The artefact that verifies the product drifted from the product.
A29: V10 | B29: Harnesses assert their own assertion count | C29: build.py check | D29: Three separate green results came from tests that never ran.
A30: V11 | B30: Signatures carry a valid competence basis | C30: product runtime | D30: Nine seeded signatures had none, found by the product checking itself.
... A32: V13 | B32: Referential integrity across orders, lots, vault, studies | C32: product runtime | D32: Only evaluable with data loaded.
B34: Standing caveat | C34: The toolchain protects these three files from the people editing them. It does not test whether a reference material producer would buy the product. The addressable share in the Market and Revenue sheet is invented, and it moves the answer more than any other input here.

Sheet Toolchain (build.py)
A1: build.py — the complete toolchain
A2: Copy column B to a file named build.py, then run: python3 build.py all. Column A is the line number only. Lines beginning with an equals sign are stored as forced text so the spreadsheet does not read them as formulas.
A4: 1 | B4: #!/usr/bin/env python3
A5: 2 | B5: """
A6: 3 | B6: build.py — the entire Lotmark toolchain in one file.
A7: 4
A8: 5 | B8: python3 build.py sync regenerate the coverage map and inject workbook figures
A9: 6 | B9: python3 build.py check run 23 preflight checks across all three artefacts
A10: 7 | B10: python3 build.py all sync, then check (the ship sequence)
A11: 8
A12: 9 | B12: Also importable as a library for `Patcher` and `cell_by_label`.
A13: 10
A14: 11 | B14: Every check here exists because the corresponding defect actually happened during this
A15: 12 | B15: build. Discipline did not catch them; a script would have. Recalculate the workbook
A16: 13 | B16: before running — openpyxl drops cached values on save.
A17: 14 | B17: """
A18: 15 | B18: import openpyxl, re, sys, os, json
A19: 16 | B19: from openpyxl.workbook.defined_name import DefinedName
A20: 17 | B20: from openpyxl.utils import quote_sheetname, absolute_coordinate
A21: 18
A22: 19 | B22: XL = "/mnt/user-data/outputs/Lotmark_and_IPC_Estimate_v5.xlsx"
A23: 20 | B23: WF = "/mnt/user-data/outputs/lotmark-product-wireframe.html"
A24: 21 | B24: AP = "/mnt/user-data/outputs/lotmark-app.html"
A25: 22
A26: 23
A27: 24 | B27: # A file that carries this script inside it must not be analysed WITH this script inside
A28: 25 | B28: # it: every literal here (const PERMS={, const COVERAGE=[, guard('...')) would be read as
A29: 26 | B29: # application code. sync() found its own embedded copy and patched the wrong place.
A30: 27 | B30: # Strip the carrier before reading, and never write inside it.
A31: 28 | B31: EMBED_OPEN = '<script type="text/plain" id="build-src">'
A32: 29 | B32: EMBED_CLOSE = '</script>'
A33: 30
A34: 31 | B34: def strip_embedded(src):
A35: 32 | B35: i = src.find(EMBED_OPEN)
A36: 33 | B36: if i == -1:
A37: 34 | B37: return src
A38: 35 | B38: j = src.find(EMBED_CLOSE, i)
A39: 36 | B39: return src[:i] + src[j + len(EMBED_CLOSE):]
A40: 37
A41: 38 | B41: def split_embedded(src):
A42: 39 | B42: i = src.find(EMBED_OPEN)
A43: 40 | B43: if i == -1:
A44: 41 | B44: return src, "", ""
A45: 42 | B45: j = src.find(EMBED_CLOSE, i) + len(EMBED_CLOSE)
A46: 43 | B46: return src[:i], src[i:j], src[j:]
A47: 44
A48: 45 | B48: # ══════════════════ PATCHING LIBRARY ══════════════════
A49: 46
A50: 47 | B50: class Patcher:
A51: 48 | B51: def __init__(self, path, comment=("/*", "*/"), marker="PATCHLIB-APPLIED"):
A52: 49 | B52: self.path, self.c, self.marker = path, comment, marker
A53: 50 | B53: self.s = open(path).read()
A54: 51 | B54: self.applied = set(re.findall(rf"{re.escape(marker)}:(\S+)", self.s))
A55: 52 | B55: self.done, self.skipped = [], []
A56: 53
A57: 54 | B57: def apply(self, pid, old, new, allow_missing=False):
A58: 55 | B58: if pid in self.applied:
A59: 56 | B59: self.skipped.append(pid); print(f" skip {pid} (already applied)"); return False
A60: 57 | B60: n = self.s.count(old)
A61: 58 | B61: if n == 0:
A62: 59 | B62: if allow_missing:
A63: 60 | B63: print(f" skip {pid} (anchor absent, allowed)"); return False
A64: 61 | B64: raise AssertionError(f"{pid}: anchor not found")
A65: 62 | B65: if n > 1:
A66: 63 | B66: raise AssertionError(f"{pid}: anchor appears {n} times — widen it until it is unique")
A67: 64 | B67: self.s = self.s.replace(old, new, 1)
A68: 65 | B68: self._record(pid)
... A71: 68 | B71: return True
A72: 69
A73: 70 | B73: def _record(self, pid):
A74: 71 | B74: tag = f"{self.c[0]} {self.marker}:{pid} {self.c[1]}"
A75: 72 | B75: self.s = self.s.rstrip() + "\n" + tag + "\n"
A76: 73 | B76: self.applied.add(pid)
A77: 74
A78: 75 | B78: def _write(self):
A79: 76 | B79: open(self.path, "w").write(self.s)
A80: 77
A81: 78 | B81: def finish(self):
A82: 79 | B82: """Post-conditions that would have caught the duplication."""
A83: 80 | B83: fns = re.findall(r"^function\s+(\w+)\s*\(", self.s, re.M)
A84: 81 | B84: dup = sorted({f for f in fns if fns.count(f) > 1})
A85: 82 | B85: if dup:
A86: 83 | B86: raise AssertionError(f"duplicate function declarations after patching: {', '.join(dup)}")
A87: 84 | B87: consts = re.findall(r"^const\s+([A-Z_][A-Z0-9_]*)\s*=", self.s, re.M)
A88: 85 | B88: dupc = sorted({c for c in consts if consts.count(c) > 1})
A89: 86 | B89: if dupc:
A90: 87 | B90: raise AssertionError(f"duplicate constants after patching: {', '.join(dupc)}")
A91: 88 | B91: print(f"\n{len(self.done)} applied, {len(self.skipped)} already present, no duplicate declarations")
A92: 89 | B92: return True
A93: 90
A94: 91 | B94: def cell_by_label(ws, predicate, value_col, label_col=2):
A95: 92 | B95: """Resolve a workbook cell by its LABEL, never by a hardcoded coordinate.
A96: 93
A97: 94 | B97: A hardcoded 'Sheet'!C122 pointed at a paragraph of prose once rows shifted.
A98: 95 | B98: Addressing by label survives inserts, deletes and reordering.
A99: 96 | B99: """
A100: 97 | B100: for r in range(1, ws.max_row + 1):
A101: 98 | B101: v = ws.cell(row=r, column=label_col).value
A102: 99 | B102: if v and predicate(str(v)):
A103: 100 | B103: target = ws.cell(row=r, column=value_col)
...

Sheet Product Build
A1: Lotmark — Cost to Build the Product
A2: Never estimated before. This is the product itself, not any one customer's deployment. Same three-point and Monte Carlo method as the rest of the workbook.
A4: Ref | B4: Module | C4: Opt (PD) | D4: Likely (PD) | E4: Pess (PD) | F4: Expected (PD) | G4: Sigma (PD) | H4: Note
B5: Foundation
A6: A1 | B6: Discovery, domain model and architecture | C6: 24 | D6: 36 | E6: 55 | F6: =ROUND((C6+4*D6+E6)/6,0) -> 37 | G6: =ROUND((E6-C6)/6,1) -> 5.2 | H6: The three traceability closures are architecture, not features.
A7: A2 | B7: Design system and UX across ~40 screens | C7: 30 | D7: 45 | E7: 68 | F7: =ROUND((C7+4*D7+E7)/6,0) -> 46 | G7: =ROUND((E7-C7)/6,1) -> 6.3
B8: Foundation subtotal | C8: =SUM(C6:C7) -> 54 | D8: =SUM(D6:D7) -> 81 | E8: =SUM(E6:E7) -> 123 | F8: =SUM(F6:F7) -> 83
B9: Production
A10: P1 | B10: Project and production plan | C10: 20 | D10: 30 | E10: 46 | F10: =ROUND((C10+4*D10+E10)/6,0) -> 31 | G10: =ROUND((E10-C10)/6,1) -> 4.3 | H10: ISO 17034 §7.2
A11: P2 | B11: Candidate material, processing steps, packaging | C11: 16 | D11: 24 | E11: 38 | F11: =ROUND((C11+4*D11+E11)/6,0) -> 25 | G11: =ROUND((E11-C11)/6,1) -> 3.7 | H11: §7.4
A12: P3 | B12: Homogeneity study and statistics | C12: 22 | D12: 34 | E12: 52 | F12: =ROUND((C12+4*D12+E12)/6,0) -> 35 | G12: =ROUND((E12-C12)/6,1) -> 5 | H12: §7.5 — produces u(bb)
A13: P4 | B13: Stability studies, short, long and ongoing | C13: 24 | D13: 36 | E13: 55 | F13: =ROUND((C13+4*D13+E13)/6,0) -> 37 | G13: =ROUND((E13-C13)/6,1) -> 5.2 | H13: §7.6 — produces shelf life and transport class
A14: P5 | B14: Characterisation and interlaboratory comparison | C14: 20 | D14: 30 | E14: 48 | F14: =ROUND((C14+4*D14+E14)/6,0) -> 31 | G14: =ROUND((E14-C14)/6,1) -> 4.7 | H14: §7.7 — produces u(char)
A15: P6 | B15: Property values and uncertainty budget engine | C15: 26 | D15: 38 | E15: 58 | F15: =ROUND((C15+4*D15+E15)/6,0) -> 39 | G15: =ROUND((E15-C15)/6,1) -> 5.3 | H15: §7.8 — derived, never typed
A16: P7 | B16: Value authorisation workflow | C16: 14 | D16: 22 | E16: 34 | F16: =ROUND((C16+4*D16+E16)/6,0) -> 23 | G16: =ROUND((E16-C16)/6,1) -> 3.3 | H16: §6.2 — non-subcontractable, SoD enforced
A17: P8 | B17: Lot register, supersession and expiry | C17: 20 | D17: 30 | E17: 46 | F17: =ROUND((C17+4*D17+E17)/6,0) -> 31 | G17: =ROUND((E17-C17)/6,1) -> 4.3 | H17: §7.9
B18: Production subtotal | C18: =SUM(C10:C17) -> 162 | D18: =SUM(D10:D17) -> 244 | E18: =SUM(E10:E17) -> 377 | F18: =SUM(F10:F17) -> 252
B19: Certification
A20: C1 | B20: Certificate generation from authorised values | C20: 22 | D20: 32 | E20: 50 | F20: =ROUND((C20+4*D20+E20)/6,0) -> 33 | G20: =ROUND((E20-C20)/6,1) -> 4.7 | H20: ISO Guide 31
A21: C2 | B21: Template designer and versioning | C21: 26 | D21: 38 | E21: 58 | F21: =ROUND((C21+4*D21+E21)/6,0) -> 39 | G21: =ROUND((E21-C21)/6,1) -> 5.3 | H21: The multi-tenant hinge
A22: C3 | B22: Registry, reissue, diff and holder list | C22: 20 | D22: 30 | E22: 46 | F22: =ROUND((C22+4*D22+E22)/6,0) -> 31 | G22: =ROUND((E22-C22)/6,1) -> 4.3 | H22: Closure 2
B23: Certification subtotal | C23: =SUM(C20:C22) -> 68 | D23: =SUM(D20:D22) -> 100 | E23: =SUM(E20:E22) -> 154 | F23: =SUM(F20:F22) -> 103
B24: Distribution
A25: D1 | B25: Catalogue and listing rules | C25: 14 | D25: 22 | E25: 34 | F25: =ROUND((C25+4*D25+E25)/6,0) -> 23 | G25: =ROUND((E25-C25)/6,1) -> 3.3
A26: D2 | B26: Entitlement engine and verification workflow | C26: 18 | D26: 26 | E26: 40 | F26: =ROUND((C26+4*D26+E26)/6,0) -> 27 | G26: =ROUND((E26-C26)/6,1) -> 3.7
A27: D3 | B27: Orders and lot allocation | C27: 20 | D27: 30 | E27: 46 | F27: =ROUND((C27+4*D27+E27)/6,0) -> 31 | G27: =ROUND((E27-C27)/6,1) -> 4.3 | H27: Allocation at the line makes the holder list computable
A28: D4 | B28: Dispatch and cold chain | C28: 22 | D28: 32 | E28: 50 | F28: =ROUND((C28+4*D28+E28)/6,0) -> 33 | G28: =ROUND((E28-C28)/6,1) -> 4.7 | H28: §7.10
A29: D5 | B29: Customer accounts and laboratory vault | C29: 24 | D29: 36 | E29: 55 | F29: =ROUND((C29+4*D29+E29)/6,0) -> 37 | G29: =ROUND((E29-C29)/6,1) -> 5.2 | H29: The second product, built as a surface on the first
A30: D6 | B30: Public certificate retrieval API | C30: 12 | D30: 18 | E30: 28 | F30: =ROUND((C30+4*D30+E30)/6,0) -> 19 | G30: =ROUND((E30-C30)/6,1) -> 2.7 | H30: Distribution strategy, not a feature
B31: Distribution subtotal | C31: =SUM(C25:C30) -> 110 | D31: =SUM(D25:D30) -> 164 | E31: =SUM(E25:E30) -> 253 | F31: =SUM(F25:F30) -> 170
B32: Compliance
A33: Q1 | B33: ISO 17034 conformance engine and clause map | C33: 24 | D33: 36 | E33: 55 | F33: =ROUND((C33+4*D33+E33)/6,0) -> 37 | G33: =ROUND((E33-C33)/6,1) -> 5.2 | H33: The reason a producer buys
A34: Q2 | B34: Audit ledger, hash chain, verify and export | C34: 16 | D34: 24 | E34: 38 | F34: =ROUND((C34+4*D34+E34)/6,0) -> 25 | G34: =ROUND((E34-C34)/6,1) -> 3.7 | H34: §8.4
A35: Q3 | B35: Equipment, calibration and impact query | C35: 16 | D35: 24 | E35: 38 | F35: =ROUND((C35+4*D35+E35)/6,0) -> 25 | G35: =ROUND((E35-C35)/6,1) -> 3.7 | H35: Closure 1
A36: Q4 | B36: Competence register, dated, enforced at signing | C36: 14 | D36: 20 | E36: 32 | F36: =ROUND((C36+4*D36+E36)/6,0) -> 21 | G36: =ROUND((E36-C36)/6,1) -> 3 | H36: Closure 3 — §6.3
A37: Q5 | B37: Subcontractor register with forbidden-activity block | C37: 10 | D37: 15 | E37: 24 | F37: =ROUND((C37+4*D37+E37)/6,0) -> 16 | G37: =ROUND((E37-C37)/6,1) -> 2.3 | H37: §6.2
A38: Q6 | B38: Complaints, nonconformity and CAPA | C38: 18 | D38: 26 | E38: 40 | F38: =ROUND((C38+4*D38+E38)/6,0) -> 27 | G38: =ROUND((E38-C38)/6,1) -> 3.7 | H38: §8.6, §8.7
B39: Compliance subtotal | C39: =SUM(C33:C38) -> 98 | D39: =SUM(D33:D38) -> 145 | E39: =SUM(E33:E38) -> 227 | F39: =SUM(F33:F38) -> 151
B40: Platform
A41: X1 | B41: Multi-tenancy, isolation and data residency | C41: 30 | D41: 45 | E41: 70 | F41: =ROUND((C41+4*D41+E41)/6,0) -> 47 | G41: =ROUND((E41-C41)/6,1) -> 6.7 | H41: Government producers require in-country hosting
A42: X2 | B42: Identity, RBAC and segregation-of-duties engine | C42: 24 | D42: 36 | E42: 55 | F42: =ROUND((C42+4*D42+E42)/6,0) -> 37 | G42: =ROUND((E42-C42)/6,1) -> 5.2
A43: X3 | B43: Tenant settings, numbering series, storage classes | C43: 14 | D43: 22 | E43: 34 | F43: =ROUND((C43+4*D43+E43)/6,0) -> 23 | G43: =ROUND((E43-C43)/6,1) -> 3.3 | H43: Existing series must continue unbroken
A44: X4 | B44: Integration framework: LIMS, ERP, courier, payment | C44: 26 | D44: 40 | E44: 62 | F44: =ROUND((C44+4*D44+E44)/6,0) -> 41 | G44: =ROUND((E44-C44)/6,1) -> 6 | H44: Manual entry path ships first; integration is the upgrade
A45: X5 | B45: Analytics and MIS | C45: 20 | D45: 30 | E45: 46 | F45: =ROUND((C45+4*D45+E45)/6,0) -> 31 | G45: =ROUND((E45-C45)/6,1) -> 4.3
A46: X6 | B46: Notification service | C46: 12 | D46: 18 | E46: 28 | F46: =ROUND((C46+4*D46+E46)/6,0) -> 19 | G46: =ROUND((E46-C46)/6,1) -> 2.7
B47: Platform subtotal | C47: =SUM(C41:C46) -> 126 | D47: =SUM(D41:D46) -> 191 | E47: =SUM(E41:E46) -> 295 | F47: =SUM(F41:F46) -> 198
B48: Field
A49: F1 | B49: Customer mobile: QR scan and vault | C49: 24 | D49: 36 | E49: 55 | F49: =ROUND((C49+4*D49+E49)/6,0) -> 37 | G49: =ROUND((E49-C49)/6,1) -> 5.2
A50: F2 | B50: Dispatch handheld | C50: 18 | D50: 26 | E50: 40 | F50: =ROUND((C50+4*D50+E50)/6,0) -> 27 | G50: =ROUND((E50-C50)/6,1) -> 3.7
B51: Field subtotal | C51: =SUM(C49:C50) -> 42 | D51: =SUM(D49:D50) -> 62 | E51: =SUM(E49:E50) -> 95 | F51: =SUM(F49:F50) -> 64
B52: Quality assurance
A53: QA1 | B53: Test strategy and cases | C53: 16 | D53: 24 | E53: 38 | F53: =ROUND((C53+4*D53+E53)/6,0) -> 25 | G53: =ROUND((E53-C53)/6,1) -> 3.7
A54: QA2 | B54: Functional and regression | C54: 40 | D54: 60 | E54: 92 | F54: =ROUND((C54+4*D54+E54)/6,0) -> 62 | G54: =ROUND((E54-C54)/6,1) -> 8.7
A55: QA3 | B55: Automation | C55: 30 | D55: 45 | E55: 68 | F55: =ROUND((C55+4*D55+E55)/6,0) -> 46 | G55: =ROUND((E55-C55)/6,1) -> 6.3
A56: QA4 | B56: Performance | C56: 12 | D56: 18 | E56: 28 | F56: =ROUND((C56+4*D56+E56)/6,0) -> 19 | G56: =ROUND((E56-C56)/6,1) -> 2.7
A57: QA5 | B57: Accessibility | C57: 14 | D57: 20 | E57: 32 | F57: =ROUND((C57+4*D57+E57)/6,0) -> 21 | G57: =ROUND((E57-C57)/6,1) -> 3
A58: QA6 | B58: Security engineering and penetration test | C58: 16 | D58: 24 | E58: 38 | F58: =ROUND((C58+4*D58+E58)/6,0) -> 25 | G58: =ROUND((E58-C58)/6,1) -> 3.7
B59: Quality assurance subtotal | C59: =SUM(C53:C58) -> 128 | D59: =SUM(D53:D58) -> 191 | E59: =SUM(E53:E58) -> 296 | F59: =SUM(F53:F58) -> 198
B60: Product management
A61: PM1 | B61: Product and delivery management | C61: 50 | D61: 75 | E61: 115 | F61: =ROUND((C61+4*D61+E61)/6,0) -> 78 | G61: =ROUND((E61-C61)/6,1) -> 10.8
A62: PM2 | B62: Documentation and standard operating procedures | C62: 16 | D62: 24 | E62: 38 | F62: =ROUND((C62+4*D62+E62)/6,0) -> 25 | G62: =ROUND((E62-C62)/6,1) -> 3.7
A63: PM3 | B63: Launch, onboarding and migration tooling | C63: 14 | D63: 22 | E63: 34 | F63: =ROUND((C63+4*D63+E63)/6,0) -> 23 | G63: =ROUND((E63-C63)/6,1) -> 3.3 | H63: Producers arrive with a spreadsheet or a PDF list
B64: Product management subtotal | C64: =SUM(C61:C63) -> 80 | D64: =SUM(D61:D63) -> 121 | E64: =SUM(E61:E63) -> 187 | F64: =SUM(F61:F63) -> 126
B65: TOTAL BASE (P50 basis) | C65: =C8+C18+C23+C31+C39+C47+C51+C59+C64 -> 868 | D65: =D8+D18+D23+D31+D39+D47+D51+D59+D64 -> 1299 | E65: =E8+E18+E23+E31+E39+E47+E51+E59+E64 -> 2007 | F65: =F8+F18+F23+F31+F39+F47+F51+F59+F64 -> 1345
B67: MONTE CARLO — 60,000 iterations, correlation 0.5, five product risks sampled inside the run
B68: P50 — even odds | C68: 1557 | D68: person-days | H68: Never bid or budget this.
B69: P80 — RECOMMENDED BUILD BUDGET | C69: 1676 | D69: person-days | H69: Same standard used for the IPC bid basis.
B70: P90 — conservative | C70: 1737 | D70: person-days | H70: If the runway is fixed and cannot extend.
B72: Build cost at the blended rate | C72: =ROUND(C69*'Team & Rate Card'!$E$16/10000000,2) -> 2.54 | D72: INR crore | H72: Compare against the INR 5.62 crore a single bespoke customer build was priced at.
B74: The finding | C74: The product costs less to build than one bespoke customer engagement was priced at. That is the whole argument for productising: the same money buys an asset that can be sold repeatedly rather than a deliverable that can be sold once. It also means the first customer can, in principle, fund the product.

Sheet Market & Revenue
A1: Market and Revenue Model
A2: Moved here from the wireframe. The cost side and the revenue side of the same decision now live in one file.
B4: COUNTED POPULATIONS — not estimated
A5: Ref | B5: Population | C5: Count | D5: Source | E5: Confidence | F5: Note
A6: M1 | B6: RM producers accredited under the ILAC MRA | C6: 320 | D6: ILAC Secretariat 2025 | E6: authoritative | F6: The producer TAM. Every prospect can be named.
A7: M2 | B7: Producers registered in COMAR | C7: 220 | D7: BAM COMAR guide | E7: floor | F7: Voluntary listing, so an undercount.
A8: M3 | B8: Certified reference materials listed in COMAR | C8: 11000 | D8: BAM COMAR guide | E8: floor | F8: About 50 per producer; the estate examined carries 1,341.
A9: M4 | B9: Laboratories accredited to ISO/IEC 17025 | C9: 114600 | D9: ILAC Secretariat 2025 | E9: authoritative | F9: The vault TAM, 358x the producer population.
B11: MODEL A — THE PRODUCER PLATFORM
A12: Ref | B12: Step | C12: Low | D12: Base | E12: High | F12: Basis
A13: A1 | B13: Producer universe | C13: 400 | D13: 550 | E13: 700 | F13: M1 accredited plus unaccredited producers
A14: A2 | B14: Addressable share (carry enough SKUs to need a system) | C14: 0.3 | D14: 0.35 | E14: 0.4 | F14: WEAKEST INPUT. Nobody publishes SKU counts per producer.
A15: A3 | B15: Addressable producers | C15: =ROUND(C13*C14,0) -> 120 | D15: =ROUND(D13*D14,0) -> 193 | E15: =ROUND(E13*E14,0) -> 280
A16: A4 | B16: Five-year penetration | C16: 0.15 | D16: 0.25 | E16: 0.4 | F16: Vertical SaaS into a listable population
A17: A5 | B17: Customers | C17: =ROUND(C15*C16,0) -> 18 | D17: =ROUND(D15*D16,0) -> 48 | E17: =ROUND(E15*E16,0) -> 112
A18: A6 | B18: Annual contract value (INR lakh) | C18: 25 | D18: 50 | E18: 92 | F18: Benchmarked against mid-market LIMS
A19: A7 | B19: Annual recurring revenue (INR Cr) | C19: =C17*C18/100 -> 4.5 | D19: =D17*D18/100 -> 24 | E19: =E17*E18/100 -> 103.04
B21: MODEL B — THE LABORATORY VAULT
A22: Ref | B22: Step | C22: Low | D22: Base | E22: High | F22: Basis
A23: B1 | B23: Accredited laboratory universe | C23: 114600 | D23: 114600 | E23: 114600 | F23: M4, an authoritative count
A24: B2 | B24: Addressable share (hold enough standards to care) | C24: 0.3 | D24: 0.4 | E24: 0.5 | F24: WEAKEST INPUT. Untested.
A25: B3 | B25: Addressable laboratories | C25: =ROUND(C23*C24,0) -> 34380 | D25: =ROUND(D23*D24,0) -> 45840 | E25: =ROUND(E23*E24,0) -> 57300
A26: B4 | B26: Five-year penetration | C26: 0.005 | D26: 0.02 | E26: 0.05 | F26: Self-serve, low touch, seeded by producers
A27: B5 | B27: Customers | C27: =ROUND(C25*C26,0) -> 172 | D27: =ROUND(D25*D26,0) -> 917 | E27: =ROUND(E25*E26,0) -> 2865
A28: B6 | B28: Annual contract value (INR lakh) | C28: 1 | D28: 2.5 | E28: 5 | F28: Per-laboratory subscription
A29: B7 | B29: Annual recurring revenue (INR Cr) | C29: =C27*C28/100 -> 1.72 | D29: =D27*D28/100 -> 22.925 | E29: =E27*E28/100 -> 143.25
B31: THE CONTRADICTION THIS SHEET EXISTS TO SURFACE
B32: Base ACV assumed for a producer (INR lakh/yr) | C32: =D18 -> 50
B33: Break-even licence for the largest plausible tenant | C33: =Break_Even_Licence_Lakh -> 28.1 | F33: From Scenario E: above this, that customer is cheaper commissioning bespoke.
B34: Gap | C34: =C32-C33 -> 21.9 | D34: INR lakh/yr | F34: Positive means the assumed price exceeds what the biggest customer can justify.
B36: Reading it honestly | C36: The producer market is listable but small, and the base annual contract value assumed here exceeds the break-even for the largest plausible tenant. Either the price is too high, or the largest government producers are not the segment the product is for. Two conversations with accredited producers would settle it, and would also replace the addressable share in both models — the weakest input in this entire workbook, and the one that moves the answer most.

Sheet Product Sensitivity
A1: Product Build — What Moves the Number
A2: Same treatment the IPC estimate gets. Each row is a re-run of the simulation, not a multiplier.
A4: Rank | B4: Variable | C4: Range tested | D4: P80 low (PD) | E4: P80 high (PD) | F4: Swing (PD) | G4: Reading
A5: 1 | B5: Overall estimate accuracy | C5: every module ±30% | D5: 1251 | E5: 2101 | F5: =E5-D5 -> 850 | G5: Dominates: the estimate's own accuracy, not any single decision.
A6: 2 | B6: Exogenous risks realised | C6: none fire vs all fire | D6: 1439 | E6: 1825 | F6: =E6-D6 -> 386
A7: 3 | B7: Multi-tenancy depth | C7: row isolation vs per-tenant keys | D7: 1620 | E7: 1795 | F7: =E7-D7 -> 175
A8: 4 | B8: Certificate templating | C8: one format vs a designer | D8: 1635 | E8: 1770 | F8: =E8-D8 -> 135
A9: 5 | B9: Correlation between modules | C9: independent vs strongly coupled | D9: 1639 | E9: 1731 | F9: =E9-D9 -> 92
A10: 6 | B10: Field applications | C10: dropped vs both shipped | D10: 1613 | E10: 1705 | F10: =E10-D10 -> 92
B12: P80 baseline for comparison | D12: 1675

Sheet Product Funding
A1: Product Build — Funding, Ramp and Cross-check
A2: The IPC number is defended six ways. This gives the product number the same treatment.
B4: MONTHLY PROFILE — 12-month build at P80
A5: Ref | B5: Line | C5: M1 | D5: M2 | E5: M3 | F5: M4 | G5: M5 | H5: M6 | I5: Note
A6: C1 | B6: Ramp weight (relative) | C6: 0.4 | D6: 0.7 | E6: 1 | F6: 1.15 | G6: 1.25 | H6: 1.25 | I6: Peaks mid-build, tapers into hardening.
A7: C2 | B7: Person-days | C7: =ROUND(1675*C6/11.2,0) -> 60 | D7: =ROUND(1675*D6/11.2,0) -> 105 | E7: =ROUND(1675*E6/11.2,0) -> 150 | F7: =ROUND(1675*F6/11.2,0) -> 172 | G7: =ROUND(1675*G6/11.2,0) -> 187 | H7: =ROUND(1675*H6/11.2,0) -> 187
A8: C3 | B8: FTE | C8: =ROUND(C7/21,1) -> 2.9 | D8: =ROUND(D7/21,1) -> 5 | E8: =ROUND(E7/21,1) -> 7.1 | F8: =ROUND(F7/21,1) -> 8.2 | G8: =ROUND(G7/21,1) -> 8.9 | H8: =ROUND(H7/21,1) -> 8.9
A9: C4 | B9: Spend (INR lakh) | C9: =ROUND(C7*'Team & Rate Card'!$E$16/100000,1) -> 9.1 | D9: =ROUND(D7*'Team & Rate Card'!$E$16/100000,1) -> 15.9 | E9: =ROUND(E7*'Team & Rate Card'!$E$16/100000,1) -> 22.7 | F9: =ROUND(F7*'Team & Rate Card'!$E$16/100000,1) -> 26 | G9: =ROUND(G7*'Team & Rate Card'!$E$16/100000,1) -> 28.3 | H9: =ROUND(H7*'Team & Rate Card'!$E$16/100000,1) -> 28.3
B11: Peak FTE | C11: =MAX(C8:H8) -> 8.9 | I11: First six months shown; the profile is symmetric thereafter.
B12: Total build cost (INR Cr) | C12: =ROUND(1675*'Team & Rate Card'!$E$16/10000000,2) -> 2.53
B13: Peak funding required before first revenue (INR Cr) | C13: =C12 -> 2.53 | I13: No customer revenue during the build, so peak funding equals the whole build. That is the number to raise or absorb.
B15: INDEPENDENT CROSS-CHECK — screen and entity count
A16: Ref | B16: Artefact | C16: Count | D16: PD each | E16: Total (PD) | I16: Basis
A17: X1 | B17: Application screens | C17: 37 | D17: 14 | E17: =C17*D17 -> 518 | I17: Design, build, test, accessibility per screen
A18: X2 | B18: Domain entities with full lifecycle | C18: 22 | D18: 12 | E18: =C18*D18 -> 264 | I18: Schema, validation, state machine, audit
A19: X3 | B19: Integration surfaces | C19: 9 | D19: 22 | E19: =C19*D19 -> 198 | I19: LIMS, ERP, courier, payment, identity, e-invoicing
A20: X4 | B20: Statistical routines | C20: 6 | D20: 18 | E20: =C20*D20 -> 108 | I20: ANOVA, regression, consensus, budget, tornado, holder list
A21: X5 | B21: Compliance artefacts | C21: 8 | D21: 26 | E21: =C21*D21 -> 208 | I21: Clause map, validation pack, retention, residency
B22: Cross-check total (PD) | E22: =SUM(E17:E21) -> 1296
B23: Bottom-up P80 (PD) | E23: 1675
B24: Divergence | E24: =(E22-1675)/1675 -> -0.22626866 | I24: Two methods built from different primitives. A divergence under about 20% is agreement; beyond that, reconcile before committing.

Sheet Effort - Mobile & IPRS
A1: Workstream A-G | Mobile App for IPRS/IMPRS + Admin Console
A2: Pink = scope the document omits. Green = scope found only by inspecting the live estate. Sigma = (Pess - Opt) / 6.
A4: Ref | B4: Workstream / Module | C4: Source | D4: Opt (PD) | E4: Likely (PD) | F4: Pess (PD) | G4: Expected (PD) | H4: Sigma (PD) | I4: Notes
A5: A | B5: Discovery & Architecture
A6: A1 | B6: Requirements elaboration, SRS and traceability matrix | C6: Doc A | D6: 22 | E6: 32 | F6: 50 | G6: =ROUND((D6+4*E6+F6)/6,0) -> 33 | H6: =ROUND((F6-D6)/6,1) -> 4.7 | I6: 39 obligations, no acceptance criteria.
A7: A2 | B7: Solution architecture, domain model, integration contracts | C7: Doc A | D7: 18 | E7: 28 | F7: 45 | G7: =ROUND((D7+4*E7+F7)/6,0) -> 29 | H7: =ROUND((F7-D7)/6,1) -> 4.5 | I7: Must resolve catalogue ownership against the OpenCart estate.
B8: A subtotal | D8: =SUM(D6:D7) -> 40 | E8: =SUM(E6:E7) -> 60 | F8: =SUM(F6:F7) -> 95 | G8: =SUM(G6:G7) -> 62 | H8: =ROUND(SQRT(SUMPRODUCT(H6:H7,H6:H7)),1) -> 6.5
A10: B | B10: Experience Design
A11: B1 | B11: Design system and accessible mobile UI kit | C11: Doc A §7 | D11: 18 | E11: 26 | F11: 40 | G11: =ROUND((D11+4*E11+F11)/6,0) -> 27 | H11: =ROUND((F11-D11)/6,1) -> 3.7 | I11: WCAG 2.1 AA assumed; Doc A omits the level.
A12: B2 | B12: Mobile screen design, ~55 screens, two platforms | C12: Doc A | D12: 24 | E12: 36 | F12: 52 | G12: =ROUND((D12+4*E12+F12)/6,0) -> 37 | H12: =ROUND((F12-D12)/6,1) -> 4.7
A13: B3 | B13: Admin console design, ~40 screens, four roles | C13: Doc A §6 | D13: 18 | E13: 28 | F13: 42 | G13: =ROUND((D13+4*E13+F13)/6,0) -> 29 | H13: =ROUND((F13-D13)/6,1) -> 4
B14: B subtotal | D14: =SUM(D11:D13) -> 60 | E14: =SUM(E11:E13) -> 90 | F14: =SUM(F11:F13) -> 134 | G14: =SUM(G11:G13) -> 93 | H14: =ROUND(SQRT(SUMPRODUCT(H11:H13,H11:H13)),1) -> 7.2
A16: C | B16: Mobile Application (iOS + Android)
A17: C1 | B17: App foundation, navigation, state, mobile CI/CD | C17: Doc A | D17: 24 | E17: 34 | F17: 50 | G17: =ROUND((D17+4*E17+F17)/6,0) -> 35 | H17: =ROUND((F17-D17)/6,1) -> 4.3
A18: C2 | B18: Registration, OTP, biometric, MFA, institutional onboarding | C18: Doc A §1 | D18: 20 | E18: 30 | F18: 45 | G18: =ROUND((D18+4*E18+F18)/6,0) -> 31 | H18: =ROUND((F18-D18)/6,1) -> 4.2 | I18: GSTIN validation assumed in scope.
A19: C3 | B19: IPRS/IMPRS catalogue, lot detail, CoA / LVS / SDS viewer | C19: Doc A §2.1 | D19: 28 | E19: 40 | F19: 58 | G19: =ROUND((D19+4*E19+F19)/6,0) -> 41 | H19: =ROUND((F19-D19)/6,1) -> 5 | I19: Verified 1,341 priced SKUs across the two published lists.
A20: C4 | B20: Publications and subscriptions, edition history, renewals | C20: Doc A §2.2 | D20: 15 | E20: 22 | F20: 34 | G20: =ROUND((D20+4*E20+F20)/6,0) -> 23 | H20: =ROUND((F20-D20)/6,1) -> 3.2 | I20: Overlaps the portal catalogue — see Unification.
A21: C5 | B21: Smart search, filters, predictive, voice, recommendations | C21: Doc A §3.1 | D21: 20 | E21: 30 | F21: 46 | G21: =ROUND((D21+4*E21+F21)/6,0) -> 31 | H21: =ROUND((F21-D21)/6,1) -> 4.3
A22: C6 | B22: Cart, checkout and order lifecycle | C22: NOT IN DOC | D22: 30 | E22: 45 | F22: 68 | G22: =ROUND((D22+4*E22+F22)/6,0) -> 46 | H22: =ROUND((F22-D22)/6,1) -> 6.3 | I22: GAP: Doc A defines no ordering journey despite being a sales app.
A23: C7 | B23: Payment: gateway SDK, UPI, cards, netbanking, PO approval | C23: Doc A §4 | D23: 20 | E23: 30 | F23: 46 | G23: =ROUND((D23+4*E23+F23)/6,0) -> 31 | H23: =ROUND((F23-D23)/6,1) -> 4.3 | I23: PCI scope assumed SAQ-A via hosted fields.
A24: C8 | B24: Notifications: push, SMS, email, preference centre | C24: Doc A §5.1 | D24: 12 | E24: 18 | F24: 28 | G24: =ROUND((D24+4*E24+F24)/6,0) -> 19 | H24: =ROUND((F24-D24)/6,1) -> 2.7
A25: C9 | B25: Feedback, support ticketing, FAQ, self-help | C25: Doc A §5.3 | D25: 14 | E25: 20 | F25: 30 | G25: =ROUND((D25+4*E25+F25)/6,0) -> 21 | H25: =ROUND((F25-D25)/6,1) -> 2.7
A26: C10 | B26: Accessibility engineering to WCAG 2.1 AA, both platforms | C26: Doc A §7 | D26: 16 | E26: 25 | F26: 40 | G26: =ROUND((D26+4*E26+F26)/6,0) -> 26 | H26: =ROUND((F26-D26)/6,1) -> 4
A27: C11 | B27: GIGW 3.0 mobile conformance and CERT-In cyber chapter | C27: NOT IN DOC | D27: 14 | E27: 20 | F27: 32 | G27: =ROUND((D27+4*E27+F27)/6,0) -> 21 | H27: =ROUND((F27-D27)/6,1) -> 3 | I27: GAP: GIGW 3.0's cybersecurity chapter explicitly covers mobile apps. Doc A never cites GIGW.
A28: C12 | B28: App hardening: pinning, root detection, obfuscation, cache | C28: Doc A §7 | D28: 13 | E28: 20 | F28: 32 | G28: =ROUND((D28+4*E28+F28)/6,0) -> 21 | H28: =ROUND((F28-D28)/6,1) -> 3.2
A29: C13 | B29: Store submission, release engineering, phased rollout | C29: Doc A | D29: 8 | E29: 12 | F29: 20 | G29: =ROUND((D29+4*E29+F29)/6,0) -> 13 | H29: =ROUND((F29-D29)/6,1) -> 2 | I29: Doc A's simultaneous-release clause is not achievable through store review.
B30: C subtotal | D30: =SUM(D17:D29) -> 234 | E30: =SUM(E17:E29) -> 346 | F30: =SUM(F17:F29) -> 529 | G30: =SUM(G17:G29) -> 359 | H30: =ROUND(SQRT(SUMPRODUCT(H17:H29,H17:H29)),1) -> 14.2
A32: D | B32: Admin Console (web)
A33: D1 | B33: Console foundation, four-role RBAC, audit instrumentation | C33: Doc A §6 | D33: 24 | E33: 34 | F33: 50 | G33: =ROUND((D33+4*E33+F33)/6,0) -> 35 | H33: =ROUND((F33-D33)/6,1) -> 4.3
A34: D2 | B34: IPRS Admin: lots, batches, expiry, stock signals | C34: Doc A §6 | D34: 22 | E34: 32 | F34: 48 | G34: =ROUND((D34+4*E34+F34)/6,0) -> 33 | H34: =ROUND((F34-D34)/6,1) -> 4.3
A35: D3 | B35: CoA and Lot Validity Statement generation engine | C35: Doc A §2.1 | D35: 16 | E35: 24 | F35: 38 | G35: =ROUND((D35+4*E35+F35)/6,0) -> 25 | H35: =ROUND((F35-D35)/6,1) -> 3.7
A36: D4 | B36: Price-tier engine and government-organisation assignment | C36: Doc A §4 | D36: 16 | E36: 24 | F36: 38 | G36: =ROUND((D36+4*E36+F36)/6,0) -> 25 | H36: =ROUND((F36-D36)/6,1) -> 3.7 | I36: REDUCED from v1: IPC already publishes a two-tier price list at exactly 50%. This is tier assignment, not a discount engine.
A37: D5 | B37: Verification workflow: document review, approval, revalidation | C37: Doc A §4 | D37: 18 | E37: 26 | F37: 40 | G37: =ROUND((D37+4*E37+F37)/6,0) -> 27 | H37: =ROUND((F37-D37)/6,1) -> 3.7 | I37: This, not the arithmetic, is the real control.
A38: D6 | B38: Dispatch Admin: scheduling, couriers, slips, tracking | C38: Doc A §6 | D38: 27 | E38: 40 | F38: 60 | G38: =ROUND((D38+4*E38+F38)/6,0) -> 41 | H38: =ROUND((F38-D38)/6,1) -> 5.5 | I38: Cold-chain handling absent from Doc A — risk K11.
A39: D7 | B39: Order management console, refunds, cancellations | C39: Doc A §4 | D39: 17 | E39: 25 | F39: 38 | G39: =ROUND((D39+4*E39+F39)/6,0) -> 26 | H39: =ROUND((F39-D39)/6,1) -> 3.5
A40: D8 | B40: User management and registration logs | C40: Doc A §1 | D40: 10 | E40: 15 | F40: 24 | G40: =ROUND((D40+4*E40+F40)/6,0) -> 16 | H40: =ROUND((F40-D40)/6,1) -> 2.3
A41: D9 | B41: Notification console: templates, scheduling, delivery reports | C41: Doc A §5.2 | D41: 13 | E41: 20 | F41: 30 | G41: =ROUND((D41+4*E41+F41)/6,0) -> 21 | H41: =ROUND((F41-D41)/6,1) -> 2.8
A42: D10 | B42: Feedback and ticket management, escalation | C42: Doc A §5.4 | D42: 13 | E42: 20 | F42: 30 | G42: =ROUND((D42+4*E42+F42)/6,0) -> 21 | H42: =ROUND((F42-D42)/6,1) -> 2.8
A43: D11 | B43: Search analytics and demand reporting | C43: Doc A §3.2 | D43: 15 | E43: 22 | F43: 34 | G43: =ROUND((D43+4*E43+F43)/6,0) -> 23 | H43: =ROUND((F43-D43)/6,1) -> 3.2
A44: D12 | B44: Reporting engine, role-scoped, PDF/Excel, scheduling | C44: Doc A §6 | D44: 24 | E44: 35 | F44: 52 | G44: =ROUND((D44+4*E44+F44)/6,0) -> 36 | H44: =ROUND((F44-D44)/6,1) -> 4.7
A45: D13 | B45: Immutable audit log: append-only, hash-chained, exportable | C45: Doc A | D45: 17 | E45: 25 | F45: 40 | G45: =ROUND((D45+4*E45+F45)/6,0) -> 26 | H45: =ROUND((F45-D45)/6,1) -> 3.8 | I45: Required nine times with no technical means specified.
B46: D subtotal | D46: =SUM(D33:D45) -> 232 | E46: =SUM(E33:E45) -> 342 | F46: =SUM(F33:F45) -> 522 | G46: =SUM(G33:G45) -> 355 | H46: =ROUND(SQRT(SUMPRODUCT(H33:H45,H33:H45)),1) -> 13.7
A48: E | B48: Platform & Integration
A49: E1 | B49: API platform: catalogue, lot, order, identity services | C49: Doc A | D49: 48 | E49: 70 | F49: 105 | G49: =ROUND((D49+4*E49+F49)/6,0) -> 72 | H49: =ROUND((F49-D49)/6,1) -> 9.5
A50: E2 | B50: Document generation: CoA, LVS, GST invoice, dispatch slip | C50: Doc A | D50: 20 | E50: 30 | F50: 46 | G50: =ROUND((D50+4*E50+F50)/6,0) -> 31 | H50: =ROUND((F50-D50)/6,1) -> 4.3
A51: E3 | B51: Payment gateway and settlement reconciliation | C51: Doc A §4 | D51: 8 | E51: 12 | F51: 20 | G51: =ROUND((D51+4*E51+F51)/6,0) -> 13 | H51: =ROUND((F51-D51)/6,1) -> 2
A52: E4 | B52: Courier API integration and tracking webhooks | C52: Doc A | D52: 10 | E52: 15 | F52: 24 | G52: =ROUND((D52+4*E52+F52)/6,0) -> 16 | H52: =ROUND((F52-D52)/6,1) -> 2.3
A53: E5 | B53: Tally / ERP posting, reconciliation, GST e-invoicing (IRN) | C53: Doc A | D53: 14 | E53: 20 | F53: 32 | G53: =ROUND((D53+4*E53+F53)/6,0) -> 21 | H53: =ROUND((F53-D53)/6,1) -> 3 | I53: IRN generation is unmentioned in Doc A but mandatory above threshold.
A54: E6 | B54: Pin-code serviceability API | C54: Doc A | D54: 3 | E54: 5 | F54: 9 | G54: =ROUND((D54+4*E54+F54)/6,0) -> 5 | H54: =ROUND((F54-D54)/6,1) -> 1
A55: E7 | B55: SMS and email integration incl. TRAI DLT registration | C55: Doc A | D55: 8 | E55: 12 | F55: 20 | G55: =ROUND((D55+4*E55+F55)/6,0) -> 13 | H55: =ROUND((F55-D55)/6,1) -> 2 | I55: DLT is mandatory in India and unmentioned.
A56: E8 | B56: IP Online federation and SSO | C56: Doc A | D56: 17 | E56: 25 | F56: 40 | G56: =ROUND((D56+4*E56+F56)/6,0) -> 26 | H56: =ROUND((F56-D56)/6,1) -> 3.8 | I56: Verified target: iponline.ipc.gov.in is a separate live system.
A57: E9 | B57: LIMS / QC ingest to source Certificate of Analysis data | C57: NOT IN DOC | D57: 16 | E57: 24 | F57: 40 | G57: =ROUND((D57+4*E57+F57)/6,0) -> 25 | H57: =ROUND((F57-D57)/6,1) -> 4 | I57: GAP CONFIRMED: lot data is published today as a manually maintained PDF. There is no evident digital source for CoA content.
A58: E10 | B58: Five-lot history backfill and lot data structuring | C58: NOT IN DOC | D58: 8 | E58: 14 | F58: 24 | G58: =ROUND((D58+4*E58+F58)/6,0) -> 15 | H58: =ROUND((F58-D58)/6,1) -> 2.7 | I58: GAP: IPC publishes one previous lot; Doc A requires five.
A59: E11 | B59: Infrastructure, IaC, environments, CI/CD, observability, DR | C59: Doc A §7 | D59: 30 | E59: 45 | F59: 68 | G59: =ROUND((D59+4*E59+F59)/6,0) -> 46 | H59: =ROUND((F59-D59)/6,1) -> 6.3 | I59: RTO/RPO undefined in Doc A; Doc B values assumed.
A60: E12 | B60: Security engineering, CERT-In audit support, VAPT | C60: Doc A §7 | D60: 20 | E60: 30 | F60: 48 | G60: =ROUND((D60+4*E60+F60)/6,0) -> 31 | H60: =ROUND((F60-D60)/6,1) -> 4.7
B61: E subtotal | D61: =SUM(D49:D60) -> 202 | E61: =SUM(E49:E60) -> 302 | F61: =SUM(F49:F60) -> 476 | G61: =SUM(G49:G60) -> 314 | H61: =ROUND(SQRT(SUMPRODUCT(H49:H60,H49:H60)),1) -> 15.2
A63: F | B63: Quality Assurance
A64: F1 | B64: Test strategy, cases, RTM linkage | C64: Doc A | D64: 18 | E64: 26 | F64: 40 | G64: =ROUND((D64+4*E64+F64)/6,0) -> 27 | H64: =ROUND((F64-D64)/6,1) -> 3.7
A65: F2 | B65: Functional and regression testing | C65: Doc A | D65: 45 | E65: 68 | F65: 100 | G65: =ROUND((D65+4*E65+F65)/6,0) -> 70 | H65: =ROUND((F65-D65)/6,1) -> 9.2
A66: F3 | B66: Test automation: API, UI, device farm | C66: Doc A | D66: 35 | E66: 52 | F66: 78 | G66: =ROUND((D66+4*E66+F66)/6,0) -> 54 | H66: =ROUND((F66-D66)/6,1) -> 7.2
A67: F4 | B67: Performance and load testing | C67: Doc A | D67: 14 | E67: 20 | F67: 32 | G67: =ROUND((D67+4*E67+F67)/6,0) -> 21 | H67: =ROUND((F67-D67)/6,1) -> 3 | I67: No volumetrics stated; thresholds must be agreed.
A68: F5 | B68: Accessibility conformance testing and remediation | C68: Doc A §7 | D68: 14 | E68: 20 | F68: 32 | G68: =ROUND((D68+4*E68+F68)/6,0) -> 21 | H68: =ROUND((F68-D68)/6,1) -> 3
A69: F6 | B69: Security testing and two VAPT cycles | C69: Doc A §7 | D69: 18 | E69: 26 | F69: 40 | G69: =ROUND((D69+4*E69+F69)/6,0) -> 27 | H69: =ROUND((F69-D69)/6,1) -> 3.7
A70: F7 | B70: UAT support and defect triage | C70: Doc A | D70: 20 | E70: 30 | F70: 46 | G70: =ROUND((D70+4*E70+F70)/6,0) -> 31 | H70: =ROUND((F70-D70)/6,1) -> 4.3
B71: F subtotal | D71: =SUM(D64:D70) -> 164 | E71: =SUM(E64:E70) -> 242 | F71: =SUM(F64:F70) -> 368 | G71: =SUM(G64:G70) -> 251 | H71: =ROUND(SQRT(SUMPRODUCT(H64:H70,H64:H70)),1) -> 14.2
A73: G | B73: Programme Management & Enablement
A74: G1 | B74: Programme and delivery management | C74: — | D74: 60 | E74: 90 | F74: 135 | G74: =ROUND((D74+4*E74+F74)/6,0) -> 93 | H74: =ROUND((F74-D74)/6,1) -> 12.5
A75: G2 | B75: Business analysis and requirements governance | C75: — | D75: 25 | E75: 38 | F75: 56 | G75: =ROUND((D75+4*E75+F75)/6,0) -> 39 | H75: =ROUND((F75-D75)/6,1) -> 5.2
A76: G3 | B76: Documentation: SRS, HLD, LLD, manuals, SOPs | C76: — | D76: 18 | E76: 28 | F76: 44 | G76: =ROUND((D76+4*E76+F76)/6,0) -> 29 | H76: =ROUND((F76-D76)/6,1) -> 4.3
A77: G4 | B77: Training and train-the-trainer, four admin roles | C77: — | D77: 12 | E77: 18 | F77: 28 | G77: =ROUND((D77+4*E77+F77)/6,0) -> 19 | H77: =ROUND((F77-D77)/6,1) -> 2.7
A78: G5 | B78: Go-live, cutover, eight-week hypercare | C78: — | D78: 20 | E78: 30 | F78: 48 | G78: =ROUND((D78+4*E78+F78)/6,0) -> 31 | H78: =ROUND((F78-D78)/6,1) -> 4.7
B79: G subtotal | D79: =SUM(D74:D78) -> 135 | E79: =SUM(E74:E78) -> 204 | F79: =SUM(F74:F78) -> 311 | G79: =SUM(G74:G78) -> 211 | H79: =ROUND(SQRT(SUMPRODUCT(H74:H78,H74:H78)),1) -> 15.2
B81: TOTAL BASE EFFORT (P50, before risk reserve) | D81: =D8+D14+D30+D46+D61+D71+D79 -> 1067 | E81: =E8+E14+E30+E46+E61+E71+E79 -> 1586 | F81: =F8+F14+F30+F46+F61+F71+F79 -> 2435 | G81: =G8+G14+G30+G46+G61+G71+G79 -> 1645 | H81: =ROUND(SQRT(H8^2+H14^2+H30^2+H46^2+H61^2+H71^2+H79^2),1) -> 33.9

Sheet Effort - Website
A1: Workstream H-S | Website Redesign, Replatform and Migration
A2: Pink = scope the document omits. Green = scope found only by inspecting the live estate. Sigma = (Pess - Opt) / 6.
A4: Ref | B4: Workstream / Module | C4: Source | D4: Opt (PD) | E4: Likely (PD) | F4: Pess (PD) | G4: Expected (PD) | H4: Sigma (PD) | I4: Notes
A5: H | B5: Discovery & Content Strategy
A6: H1 | B6: Discovery, workshops, information architecture, sitemap | C6: Doc B §1.1 | D6: 18 | E6: 28 | F6: 44 | G6: =ROUND((D6+4*E6+F6)/6,0) -> 29 | H6: =ROUND((F6-D6)/6,1) -> 4.3
A7: H2 | B7: Content audit and migration plan | C7: NOT IN DOC | D7: 8 | E7: 13 | F7: 22 | G7: =ROUND((D7+4*E7+F7)/6,0) -> 14 | H7: =ROUND((F7-D7)/6,1) -> 2.3 | I7: GAP, but now scoped from the live estate rather than assumed.
B8: H subtotal | D8: =SUM(D6:D7) -> 26 | E8: =SUM(E6:E7) -> 41 | F8: =SUM(F6:F7) -> 66 | G8: =SUM(G6:G7) -> 43 | H8: =ROUND(SQRT(SUMPRODUCT(H6:H7,H6:H7)),1) -> 4.9
A10: I | B10: Experience Design
A11: I1 | B11: GIGW 3.0 / DBIM design system, bilingual type and grid | C11: Doc B §1.1 | D11: 20 | E11: 30 | F11: 46 | G11: =ROUND((D11+4*E11+F11)/6,0) -> 31 | H11: =ROUND((F11-D11)/6,1) -> 4.3 | I11: 88 mandatory GIGW guidelines across four domains.
A12: I2 | B12: Template design, ~28 page templates | C12: Doc B §1.3 | D12: 28 | E12: 42 | F12: 62 | G12: =ROUND((D12+4*E12+F12)/6,0) -> 43 | H12: =ROUND((F12-D12)/6,1) -> 5.7
A13: I3 | B13: Commerce and account journey design | C13: Doc B §1.7 | D13: 10 | E13: 16 | F13: 26 | G13: =ROUND((D13+4*E13+F13)/6,0) -> 17 | H13: =ROUND((F13-D13)/6,1) -> 2.7
B14: I subtotal | D14: =SUM(D11:D13) -> 58 | E14: =SUM(E11:E13) -> 88 | F14: =SUM(F11:F13) -> 134 | G14: =SUM(G11:G13) -> 91 | H14: =ROUND(SQRT(SUMPRODUCT(H11:H13,H11:H13)),1) -> 7.6
A16: J | B16: CMS Platform
A17: J1 | B17: CMS platform setup, hardening, environments | C17: Doc B §1.2 | D17: 16 | E17: 24 | F17: 38 | G17: =ROUND((D17+4*E17+F17)/6,0) -> 25 | H17: =ROUND((F17-D17)/6,1) -> 3.7 | I17: Replaces Joomla.
A18: J2 | B18: RBAC and editorial approval workflow | C18: Doc B §1.2.1 | D18: 14 | E18: 20 | F18: 32 | G18: =ROUND((D18+4*E18+F18)/6,0) -> 21 | H18: =ROUND((F18-D18)/6,1) -> 3
A19: J3 | B19: Bilingual WYSIWYG authoring, spellcheck, media embed | C19: Doc B §1.2.1 | D19: 8 | E19: 12 | F19: 20 | G19: =ROUND((D19+4*E19+F19)/6,0) -> 13 | H19: =ROUND((F19-D19)/6,1) -> 2
A20: J4 | B20: Scheduling, auto-publish, auto-expire, expiry alerts | C20: Doc B §1.2.1 | D20: 7 | E20: 10 | F20: 16 | G20: =ROUND((D20+4*E20+F20)/6,0) -> 11 | H20: =ROUND((F20-D20)/6,1) -> 1.5
A21: J5 | B21: Backup, versioning, rollback, version compare | C21: Doc B §1.2.1 | D21: 8 | E21: 12 | F21: 20 | G21: =ROUND((D21+4*E21+F21)/6,0) -> 13 | H21: =ROUND((F21-D21)/6,1) -> 2
A22: J6 | B22: Immutable CMS audit trail and exportable logs | C22: Doc B §1.2.1 | D22: 12 | E22: 18 | F22: 28 | G22: =ROUND((D22+4*E22+F22)/6,0) -> 19 | H22: =ROUND((F22-D22)/6,1) -> 2.7
A23: J7 | B23: Archival engine: rules, retention, archive section, labelling | C23: Doc B §1.2.4 | D23: 14 | E23: 20 | F23: 32 | G23: =ROUND((D23+4*E23+F23)/6,0) -> 21 | H23: =ROUND((F23-D23)/6,1) -> 3 | I23: Live estate shows a 2023 G20 banner and a 2019 site map — the requirement is well founded.
B24: J subtotal | D24: =SUM(D17:D23) -> 79 | E24: =SUM(E17:E23) -> 116 | F24: =SUM(F17:F23) -> 186 | G24: =SUM(G17:G23) -> 123 | H24: =ROUND(SQRT(SUMPRODUCT(H17:H23,H17:H23)),1) -> 7
A26: K | B26: Content, Multimedia & Facilities
A27: K1 | B27: Video platform integration, player, captions, transcripts | C27: Doc B §1.2.2 | D27: 18 | E27: 28 | F27: 44 | G27: =ROUND((D27+4*E27+F27)/6,0) -> 29 | H27: =ROUND((F27-D27)/6,1) -> 4.3
A28: K2 | B28: Image wizard: gallery, resize, alt text, bulk upload | C28: Doc B §1.2.2 | D28: 10 | E28: 16 | F28: 26 | G28: =ROUND((D28+4*E28+F28)/6,0) -> 17 | H28: =ROUND((F28-D28)/6,1) -> 2.7
A29: K3 | B29: Document management: versioning, indexing, secure download | C29: Doc B §1.2.3 | D29: 16 | E29: 24 | F29: 38 | G29: =ROUND((D29+4*E29+F29)/6,0) -> 25 | H29: =ROUND((F29-D29)/6,1) -> 3.7
A30: K4 | B30: Event calendar, registration, reminders, archive | C30: Doc B §1.2.3 | D30: 20 | E30: 30 | F30: 46 | G30: =ROUND((D30+4*E30+F30)/6,0) -> 31 | H30: =ROUND((F30-D30)/6,1) -> 4.3
A31: K5 | B31: FAQ and glossary modules | C31: Doc B §1.2.3 | D31: 12 | E31: 18 | F31: 28 | G31: =ROUND((D31+4*E31+F31)/6,0) -> 19 | H31: =ROUND((F31-D31)/6,1) -> 2.7
A32: K6 | B32: Polls and visitor survey with analytics | C32: Doc B §1.2.3 | D32: 10 | E32: 16 | F32: 26 | G32: =ROUND((D32+4*E32+F32)/6,0) -> 17 | H32: =ROUND((F32-D32)/6,1) -> 2.7
A33: K7 | B33: Public forum: threads, moderation, reputation, redressal | C33: Doc B §1.2.3 | D33: 30 | E33: 45 | F33: 68 | G33: =ROUND((D33+4*E33+F33)/6,0) -> 46 | H33: =ROUND((F33-D33)/6,1) -> 6.3 | I33: Largest CMS module; heaviest moderation risk.
A34: K8 | B34: Recruitment form, tracking, export, HR dashboard | C34: Doc B §1.2.3 | D34: 16 | E34: 24 | F34: 38 | G34: =ROUND((D34+4*E34+F34)/6,0) -> 25 | H34: =ROUND((F34-D34)/6,1) -> 3.7
B35: K subtotal | D35: =SUM(D27:D34) -> 132 | E35: =SUM(E27:E34) -> 201 | F35: =SUM(F27:F34) -> 314 | G35: =SUM(G27:G34) -> 209 | H35: =ROUND(SQRT(SUMPRODUCT(H27:H34,H27:H34)),1) -> 11.2
A37: L | B37: Frontend & Engagement
A38: L1 | B38: Templates, mega menu, breadcrumbs, sticky nav, cards | C38: Doc B §1.3.1 | D38: 34 | E38: 50 | F38: 74 | G38: =ROUND((D38+4*E38+F38)/6,0) -> 51 | H38: =ROUND((F38-D38)/6,1) -> 6.7
A39: L2 | B39: Personalisation widgets, quick tiles, one-click downloads | C39: Doc B §1.3.3 | D39: 12 | E39: 18 | F39: 28 | G39: =ROUND((D39+4*E39+F39)/6,0) -> 19 | H39: =ROUND((F39-D39)/6,1) -> 2.7
A40: L3 | B40: Bilingual framework and language toggle | C40: Doc B §1.1 | D40: 10 | E40: 15 | F40: 26 | G40: =ROUND((D40+4*E40+F40)/6,0) -> 16 | H40: =ROUND((F40-D40)/6,1) -> 2.7 | I40: REDUCED from v1: a Hindi site already exists at /hi/.
A41: L4 | B41: Accessibility engineering to WCAG 2.1 AA | C41: Doc B §1.1 | D41: 26 | E41: 38 | F41: 58 | G41: =ROUND((D41+4*E41+F41)/6,0) -> 39 | H41: =ROUND((F41-D41)/6,1) -> 5.3
B42: L subtotal | D42: =SUM(D38:D41) -> 82 | E42: =SUM(E38:E41) -> 121 | F42: =SUM(F38:F41) -> 186 | G42: =SUM(G38:G41) -> 125 | H42: =ROUND(SQRT(SUMPRODUCT(H38:H41,H38:H41)),1) -> 9.4
A44: M | B44: Search & AI Layer
A45: M1 | B45: Search platform, indexing, multilingual facets, relevance | C45: Doc B §1.3.2 | D45: 22 | E45: 32 | F45: 50 | G45: =ROUND((D45+4*E45+F45)/6,0) -> 33 | H45: =ROUND((F45-D45)/6,1) -> 4.7
A46: M2 | B46: Semantic / vector search and recommendations | C46: Doc B §1.1 | D46: 18 | E46: 28 | F46: 44 | G46: =ROUND((D46+4*E46+F46)/6,0) -> 29 | H46: =ROUND((F46-D46)/6,1) -> 4.3
A47: M3 | B47: Voice search and text-to-speech / speech-to-text | C47: Doc B §1.1 | D47: 13 | E47: 20 | F47: 32 | G47: =ROUND((D47+4*E47+F47)/6,0) -> 21 | H47: =ROUND((F47-D47)/6,1) -> 3.2
A48: M4 | B48: Chatbot assistant: retrieval, guardrails, escalation | C48: Doc B §1.1 | D48: 30 | E48: 45 | F48: 70 | G48: =ROUND((D48+4*E48+F48)/6,0) -> 47 | H48: =ROUND((F48-D48)/6,1) -> 6.7 | I48: Regulatory Q&A on drug alerts demands strict grounding.
A49: M5 | B49: AI auto-tagging and document classification | C49: Doc B §1.1 | D49: 16 | E49: 24 | F49: 38 | G49: =ROUND((D49+4*E49+F49)/6,0) -> 25 | H49: =ROUND((F49-D49)/6,1) -> 3.7
A50: M6 | B50: AI moderation: spam, misuse, fraud detection | C50: Doc B §1.1 | D50: 12 | E50: 18 | F50: 30 | G50: =ROUND((D50+4*E50+F50)/6,0) -> 19 | H50: =ROUND((F50-D50)/6,1) -> 3
A51: M7 | B51: AI governance: evaluation harness, accuracy testing, HITL | C51: NOT IN DOC | D51: 12 | E51: 18 | F51: 30 | G51: =ROUND((D51+4*E51+F51)/6,0) -> 19 | H51: =ROUND((F51-D51)/6,1) -> 3 | I51: GAP: seven AI features mandated with no accuracy or safety criteria.
B52: M subtotal | D52: =SUM(D45:D51) -> 123 | E52: =SUM(E45:E51) -> 185 | F52: =SUM(F45:F51) -> 294 | G52: =SUM(G45:G51) -> 193 | H52: =ROUND(SQRT(SUMPRODUCT(H45:H51,H45:H51)),1) -> 11.3
A54: N | B54: E-Commerce (replatform)
A55: N1 | B55: Catalogue, categories, filters, bulk upload, versioning | C55: Doc B §1.7.1 | D55: 20 | E55: 30 | F55: 46 | G55: =ROUND((D55+4*E55+F55)/6,0) -> 31 | H55: =ROUND((F55-D55)/6,1) -> 4.3
A56: N2 | B56: Catalogue data onboarding: 1,341 SKUs, lots, two price tiers | C56: NEW | D56: 16 | E56: 25 | F56: 42 | G56: =ROUND((D56+4*E56+F56)/6,0) -> 26 | H56: =ROUND((F56-D56)/6,1) -> 4.3 | I56: NEW: verified 702 IPRS + 639 IMPRS, currently maintained as PDFs.
A57: N3 | B57: Cart, checkout, address, shipping, tax, persistence, reorder | C57: Doc B §1.7.2 | D57: 24 | E57: 35 | F57: 52 | G57: =ROUND((D57+4*E57+F57)/6,0) -> 36 | H57: =ROUND((F57-D57)/6,1) -> 4.7
A58: N4 | B58: Payment gateway, multi-currency, retries, reconciliation | C58: Doc B §1.7.3 | D58: 14 | E58: 20 | F58: 32 | G58: =ROUND((D58+4*E58+F58)/6,0) -> 21 | H58: =ROUND((F58-D58)/6,1) -> 3
A59: N5 | B59: Order management, notifications, refunds, reports | C59: Doc B §1.7.4 | D59: 20 | E59: 30 | F59: 46 | G59: =ROUND((D59+4*E59+F59)/6,0) -> 31 | H59: =ROUND((F59-D59)/6,1) -> 4.3
A60: N6 | B60: Customer accounts, history, invoices, subscriptions, tracking | C60: Doc B §1.7.5 | D60: 17 | E60: 25 | F60: 38 | G60: =ROUND((D60+4*E60+F60)/6,0) -> 26 | H60: =ROUND((F60-D60)/6,1) -> 3.5
A61: N7 | B61: Promotions, discount codes, scheduling, banners | C61: Doc B §1.7.6 | D61: 12 | E61: 18 | F61: 28 | G61: =ROUND((D61+4*E61+F61)/6,0) -> 19 | H61: =ROUND((F61-D61)/6,1) -> 2.7
A62: N8 | B62: Sales analytics, funnels, dashboards | C62: Doc B §1.7.8 | D62: 15 | E62: 22 | F62: 34 | G62: =ROUND((D62+4*E62+F62)/6,0) -> 23 | H62: =ROUND((F62-D62)/6,1) -> 3.2
A63: N9 | B63: OpenCart data migration: products, customers, order history | C63: NEW | D63: 22 | E63: 34 | F63: 55 | G63: =ROUND((D63+4*E63+F63)/6,0) -> 36 | H63: =ROUND((F63-D63)/6,1) -> 5.5 | I63: NEW: the existing shop is live OpenCart. Neither document mentions migrating its data.
B64: N subtotal | D64: =SUM(D55:D63) -> 160 | E64: =SUM(E55:E63) -> 239 | F64: =SUM(F55:F63) -> 373 | G64: =SUM(G55:G63) -> 249 | H64: =ROUND(SQRT(SUMPRODUCT(H55:H63,H55:H63)),1) -> 12.1
A66: O | B66: Analytics, Communication & Integration
A67: O1 | B67: Visitor analytics, event and journey tracking | C67: Doc B §1.4.1 | D67: 14 | E67: 20 | F67: 32 | G67: =ROUND((D67+4*E67+F67)/6,0) -> 21 | H67: =ROUND((F67-D67)/6,1) -> 3
A68: O2 | B68: Heatmaps, funnel and behavioural analytics | C68: Doc B §1.4.3 | D68: 10 | E68: 16 | F68: 26 | G68: =ROUND((D68+4*E68+F68)/6,0) -> 17 | H68: =ROUND((F68-D68)/6,1) -> 2.7
A69: O3 | B69: MIS dashboard: widgets, drill-down, scheduled reports | C69: Doc B §1.4.4 | D69: 24 | E69: 35 | F69: 52 | G69: =ROUND((D69+4*E69+F69)/6,0) -> 36 | H69: =ROUND((F69-D69)/6,1) -> 4.7
A70: O4 | B70: DPDP consent management and Consent Manager integration | C70: Doc B §1.4.5 | D70: 18 | E70: 28 | F70: 44 | G70: =ROUND((D70+4*E70+F70)/6,0) -> 29 | H70: =ROUND((F70-D70)/6,1) -> 4.3 | I70: EXPANDED: Rules notified 13 Nov 2025; full compliance due 13 May 2027.
A71: O5 | B71: Transactional and promotional SMS/email, bilingual, analytics | C71: Doc B §1.5 | D71: 20 | E71: 30 | F71: 46 | G71: =ROUND((D71+4*E71+F71)/6,0) -> 31 | H71: =ROUND((F71-D71)/6,1) -> 4.3
A72: O6 | B72: IP Online / PvPI integration and SSO across IPC portals | C72: Doc B §1.6 | D72: 24 | E72: 35 | F72: 52 | G72: =ROUND((D72+4*E72+F72)/6,0) -> 36 | H72: =ROUND((F72-D72)/6,1) -> 4.7
B73: O subtotal | D73: =SUM(D67:D72) -> 110 | E73: =SUM(E67:E72) -> 164 | F73: =SUM(F67:F72) -> 252 | G73: =SUM(G67:G72) -> 170 | H73: =ROUND(SQRT(SUMPRODUCT(H67:H72,H67:H72)),1) -> 9.9
A75: P | B75: Content Migration
A76: P1 | B76: Migration tooling and mapping, Joomla to target | C76: NOT IN DOC | D76: 16 | E76: 24 | F76: 40 | G76: =ROUND((D76+4*E76+F76)/6,0) -> 25 | H76: =ROUND((F76-D76)/6,1) -> 4 | I76: GAP, now scoped: ~137 English menu pages plus Hindi mirror.
A77: P2 | B77: Article and document migration, ~1,500 items, plus QA | C77: NOT IN DOC | D77: 22 | E77: 34 | F77: 55 | G77: =ROUND((D77+4*E77+F77)/6,0) -> 36 | H77: =ROUND((F77-D77)/6,1) -> 5.5 | I77: GAP, now scoped: Joomla article IDs run past 1,500.
A78: P3 | B78: Hindi coverage completion and bilingual QA | C78: Doc B §1.1 | D78: 10 | E78: 15 | F78: 26 | G78: =ROUND((D78+4*E78+F78)/6,0) -> 16 | H78: =ROUND((F78-D78)/6,1) -> 2.7 | I78: REDUCED: Hindi site already exists.
A79: P4 | B79: URL redirect mapping and SEO preservation | C79: NOT IN DOC | D79: 8 | E79: 12 | F79: 20 | G79: =ROUND((D79+4*E79+F79)/6,0) -> 13 | H79: =ROUND((F79-D79)/6,1) -> 2 | I79: GAP: omitting this loses inbound links at cutover.
B80: P subtotal | D80: =SUM(D76:D79) -> 56 | E80: =SUM(E76:E79) -> 85 | F80: =SUM(F76:F79) -> 141 | G80: =SUM(G76:G79) -> 90 | H80: =ROUND(SQRT(SUMPRODUCT(H76:H79,H76:H79)),1) -> 7.6
A82: Q | B82: Infrastructure, Security & Certification
A83: Q1 | B83: NIC / MeitY hosting provisioning, IaC, environments | C83: Doc B §3.1 | D83: 20 | E83: 30 | F83: 46 | G83: =ROUND((D83+4*E83+F83)/6,0) -> 31 | H83: =ROUND((F83-D83)/6,1) -> 4.3
A84: Q2 | B84: DR site, replication, failover, drill runbooks | C84: Doc B §3.3 | D84: 18 | E84: 26 | F84: 40 | G84: =ROUND((D84+4*E84+F84)/6,0) -> 27 | H84: =ROUND((F84-D84)/6,1) -> 3.7 | I84: RTO under 4h, RPO under 15min.
A85: Q3 | B85: Monitoring, IDPS, alerting, SOC handover | C85: Doc B §2.3 | D85: 12 | E85: 18 | F85: 28 | G85: =ROUND((D85+4*E85+F85)/6,0) -> 19 | H85: =ROUND((F85-D85)/6,1) -> 2.7
A86: Q4 | B86: Security engineering and two VAPT cycles | C86: Doc B §2.4 | D86: 20 | E86: 30 | F86: 48 | G86: =ROUND((D86+4*E86+F86)/6,0) -> 31 | H86: =ROUND((F86-D86)/6,1) -> 4.7
A87: Q5 | B87: GIGW 3.0 conformance and STQC CQW certification support | C87: Doc B §1.1 | D87: 18 | E87: 28 | F87: 44 | G87: =ROUND((D87+4*E87+F87)/6,0) -> 29 | H87: =ROUND((F87-D87)/6,1) -> 4.3 | I87: EXPANDED: 88 mandatory guidelines; CQW involves document review plus frontend and backend testing.
B88: Q subtotal | D88: =SUM(D83:D87) -> 88 | E88: =SUM(E83:E87) -> 132 | F88: =SUM(F83:F87) -> 206 | G88: =SUM(G83:G87) -> 137 | H88: =ROUND(SQRT(SUMPRODUCT(H83:H87,H83:H87)),1) -> 8.9
A90: R | B90: Quality Assurance
A91: R1 | B91: Test strategy, cases, RTM across 152 obligations | C91: Doc B | D91: 16 | E91: 24 | F91: 38 | G91: =ROUND((D91+4*E91+F91)/6,0) -> 25 | H91: =ROUND((F91-D91)/6,1) -> 3.7
A92: R2 | B92: Functional and regression testing | C92: Doc B | D92: 42 | E92: 62 | F92: 94 | G92: =ROUND((D92+4*E92+F92)/6,0) -> 64 | H92: =ROUND((F92-D92)/6,1) -> 8.7
A93: R3 | B93: Test automation | C93: Doc B | D93: 28 | E93: 42 | F93: 64 | G93: =ROUND((D93+4*E93+F93)/6,0) -> 43 | H93: =ROUND((F93-D93)/6,1) -> 6
A94: R4 | B94: Performance and load testing | C94: Doc B §3.2 | D94: 12 | E94: 18 | F94: 30 | G94: =ROUND((D94+4*E94+F94)/6,0) -> 19 | H94: =ROUND((F94-D94)/6,1) -> 3 | I94: Stated sizing is current traffic, not a peak-concurrency basis.
A95: R5 | B95: Accessibility conformance testing and remediation | C95: Doc B §1.1 | D95: 16 | E95: 24 | F95: 38 | G95: =ROUND((D95+4*E95+F95)/6,0) -> 25 | H95: =ROUND((F95-D95)/6,1) -> 3.7
A96: R6 | B96: Bilingual content and cross-browser testing | C96: Doc B §1.1 | D96: 14 | E96: 20 | F96: 32 | G96: =ROUND((D96+4*E96+F96)/6,0) -> 21 | H96: =ROUND((F96-D96)/6,1) -> 3
A97: R7 | B97: UAT support and defect triage | C97: Doc B | D97: 18 | E97: 28 | F97: 44 | G97: =ROUND((D97+4*E97+F97)/6,0) -> 29 | H97: =ROUND((F97-D97)/6,1) -> 4.3
B98: R subtotal | D98: =SUM(D91:D97) -> 146 | E98: =SUM(E91:E97) -> 218 | F98: =SUM(F91:F97) -> 340 | G98: =SUM(G91:G97) -> 226 | H98: =ROUND(SQRT(SUMPRODUCT(H91:H97,H91:H97)),1) -> 13.2
A100: S | B100: Programme Management & Enablement
A101: S1 | B101: Programme and delivery management | C101: — | D101: 55 | E101: 82 | F101: 124 | G101: =ROUND((D101+4*E101+F101)/6,0) -> 85 | H101: =ROUND((F101-D101)/6,1) -> 11.5
A102: S2 | B102: Business analysis and content governance | C102: — | D102: 22 | E102: 34 | F102: 52 | G102: =ROUND((D102+4*E102+F102)/6,0) -> 35 | H102: =ROUND((F102-D102)/6,1) -> 5
A103: S3 | B103: Documentation and standard operating procedures | C103: — | D103: 16 | E103: 24 | F103: 38 | G103: =ROUND((D103+4*E103+F103)/6,0) -> 25 | H103: =ROUND((F103-D103)/6,1) -> 3.7
A104: S4 | B104: Training and train-the-trainer | C104: — | D104: 12 | E104: 18 | F104: 28 | G104: =ROUND((D104+4*E104+F104)/6,0) -> 19 | H104: =ROUND((F104-D104)/6,1) -> 2.7
A105: S5 | B105: Go-live, cutover, hypercare | C105: — | D105: 18 | E105: 28 | F105: 44 | G105: =ROUND((D105+4*E105+F105)/6,0) -> 29 | H105: =ROUND((F105-D105)/6,1) -> 4.3
B106: S subtotal | D106: =SUM(D101:D105) -> 123 | E106: =SUM(E101:E105) -> 186 | F106: =SUM(F101:F105) -> 286 | G106: =SUM(G101:G105) -> 193 | H106: =ROUND(SQRT(SUMPRODUCT(H101:H105,H101:H105)),1) -> 14
B108: TOTAL BASE EFFORT (P50, before risk reserve) | D108: =D8+D14+D24+D35+D42+D52+D64+D73+D80+D88+D98+D106 -> 1183 | E108: =E8+E14+E24+E35+E42+E52+E64+E73+E80+E88+E98+E106 -> 1776 | F108: =F8+F14+F24+F35+F42+F52+F64+F73+F80+F88+F98+F106 -> 2778 | G108: =G8+G14+G24+G35+G42+G52+G64+G73+G80+G88+G98+G106 -> 1849 | H108: =ROUND(SQRT(H8^2+H14^2+H24^2+H35^2+H42^2+H52^2+H64^2+H73^2+H80^2+H88^2+H98^2+H106^2),1) -> 35

Sheet Monte Carlo
A1: Confidence — Monte Carlo Simulation
A2: 100,000 iterations. Beta-PERT marginals on every module, correlated through a Gaussian copula, with exogenous risk events sampled inside the same run. Replaces the v2 P80-plus-EMV method.
B4: WHY THIS REPLACES THE v2 METHOD
B5: Composition error | C5: v2 added an expected value to a P80 and labelled the sum a P80. A mean plus a percentile is neither. On this distribution the v2 figure of 3,623 PD actually sits at about P81.
B6: Distribution shape | C6: v2 implied a normal spread. Task durations are bounded below and right-skewed; a normal understates the upper tail and permits negative durations. This run uses Beta-PERT, derived from the same optimistic / likely / pessimistic values already in the model.
B7: Correlation | C7: v2 multiplied sigma by 3.5, a factor chosen by hand. Here correlation is an explicit parameter with its effect shown across four values, so the assumption is visible and testable rather than buried.
B8: Double counting | C8: v2's register charged 135 PD of expected value for requirement volatility — which is exactly what the optimistic-to-pessimistic spread on all 122 modules already encodes. It is removed, and six further risks are reduced to their marginal exposure beyond the module pessimistic.
B9: Savings realisation | C9: v2 treated the unification saving as certain. Here it is sampled at 70 to 110 per cent of nominal, since savings under-deliver more often than they over-deliver.
B11: SIMULATION PARAMETERS
B12: Iterations | C12: 100,000
B13: Modules sampled | C13: 122
B14: Marginal distribution | C14: Beta-PERT from O / M / P
B15: Dependence | C15: Gaussian copula, single common factor
B16: Correlation used for headline | C16: 0.5
B17: Exogenous risk events | C17: 13
B18: Endogenous risks removed | C18: K10 (requirement volatility)
B19: Unification saving | C19: 524 PD, now computed from source modules, sampled 70–110%
B20: Random seed | C20: 20260818 (reproducible)
B22: SENSITIVITY TO THE CORRELATION ASSUMPTION
B23: Correlation | C23: P50 (PD) | D23: P70 (PD) | E23: P80 (PD) | F23: P90 (PD) | G23: P95 (PD) | H23: Reading
B24: rho = 0.0 | C24: 3446 | D24: 3574 | E24: 3619 | F24: 3670 | G24: 3708 | H24: Independent modules. Unrealistic — one team, one client, one set of ambiguities.
B25: rho = 0.3 | C25: 3431 | D25: 3572 | E25: 3652 | F25: 3756 | G25: 3838 | H25: Weak common cause. Plausible for a portfolio of unrelated projects.
B26: rho = 0.5 | C26: 3424 | D26: 3605 | E26: 3714 | F26: 3861 | G26: 3984 | H26: RECOMMENDED. Single accountable team on a single programme with shared requirement risk.
B27: rho = 0.7 | C27: 3417 | D27: 3654 | E27: 3797 | F27: 3994 | G27: 4154 | H27: Strong common cause. Appropriate if requirements remain unfrozen at award.
B29: RECOMMENDED BASIS
B30: P50 — even odds | C30: 3424 | D30: person-days | H30: Half of comparable programmes finish inside this. Never bid it.
B31: P80 — RECOMMENDED BID BASIS | C31: 3714 | D31: person-days | H31: Standard commercial basis for a fixed-price government contract.
B32: P90 — conservative | C32: 3861 | D32: person-days | H32: Use where liquidated damages bite hard or the schedule cannot move.
B33: P80 with K1 resolved pre-award | C33: 3500 | D33: person-days | H33: Asking one clarification question before pricing is worth 216 PD.
B35: Change against the v3 figure of 3,608 PD | C35: 106 | H35: Moved because the unification saving is no longer 635 PD hardcoded. Computed from the modules it actually reduces, it is 524 PD — so the earlier figure over-claimed the saving and understated the effort.
B37: DISTRIBUTION (rho = 0.5)
B38: Bucket midpoint (PD) | C38: Iterations (count)
B39: 2092 | C39: 5
B40: 2183 | C40: 5
B41: 2274 | C41: 48
B42: 2365 | C42: 155
B43: 2456 | C43: 350
B44: 2547 | C44: 786
B45: 2638 | C45: 1501
B46: 2729 | C46: 2590
B47: 2820 | C47: 3921
B48: 2911 | C48: 5495
B49: 3002 | C49: 7225
B50: 3093 | C50: 8474
... B66: 4548 | C66: 7

Sheet Scenario C Model
A1: Scenario C — Phase 1 Release, Modelled
A2: Replaces the 0.62x multiplier. Each build module is tagged to a phase; QA and programme management scale with the phase-1 build share.
A4: Ref | B4: Module | C4: Expected (PD) | D4: Phase | E4: In phase 1 (PD) | F4: Rationale where deferred
A5: A1 | B5: Requirements elaboration, SRS and traceability matrix | C5: ='Effort - Mobile & IPRS'!G6 -> 33 | D5: Phase 1 | E5: =IF(D5="Phase 1",C5,0) -> 33
A6: A2 | B6: Solution architecture, domain model, integration contracts | C6: ='Effort - Mobile & IPRS'!G7 -> 29 | D6: Phase 1 | E6: =IF(D6="Phase 1",C6,0) -> 29
A7: B1 | B7: Design system and accessible mobile UI kit | C7: ='Effort - Mobile & IPRS'!G11 -> 27 | D7: Phase 1 | E7: =IF(D7="Phase 1",C7,0) -> 27
A8: B2 | B8: Mobile screen design, ~55 screens, two platforms | C8: ='Effort - Mobile & IPRS'!G12 -> 37 | D8: Phase 2 | E8: =IF(D8="Phase 1",C8,0) -> 0 | F8: Mobile design deferred with the app.
A9: B3 | B9: Admin console design, ~40 screens, four roles | C9: ='Effort - Mobile & IPRS'!G13 -> 29 | D9: Phase 1 | E9: =IF(D9="Phase 1",C9,0) -> 29
A10: C1 | B10: App foundation, navigation, state, mobile CI/CD | C10: ='Effort - Mobile & IPRS'!G17 -> 35 | D10: Phase 2 | E10: =IF(D10="Phase 1",C10,0) -> 0 | F10: Mobile app deferred; the portal carries commerce in phase 1.
A11: C2 | B11: Registration, OTP, biometric, MFA, institutional onboarding | C11: ='Effort - Mobile & IPRS'!G18 -> 31 | D11: Phase 2 | E11: =IF(D11="Phase 1",C11,0) -> 0 | F11: Mobile app deferred; the portal carries commerce in phase 1.
A12: C3 | B12: IPRS/IMPRS catalogue, lot detail, CoA / LVS / SDS viewer | C12: ='Effort - Mobile & IPRS'!G19 -> 41 | D12: Phase 2 | E12: =IF(D12="Phase 1",C12,0) -> 0 | F12: Mobile app deferred; the portal carries commerce in phase 1.
A13: C4 | B13: Publications and subscriptions, edition history, renewals | C13: ='Effort - Mobile & IPRS'!G20 -> 23 | D13: Phase 2 | E13: =IF(D13="Phase 1",C13,0) -> 0 | F13: Mobile app deferred; the portal carries commerce in phase 1.
A14: C5 | B14: Smart search, filters, predictive, voice, recommendations | C14: ='Effort - Mobile & IPRS'!G21 -> 31 | D14: Phase 2 | E14: =IF(D14="Phase 1",C14,0) -> 0 | F14: Mobile app deferred; the portal carries commerce in phase 1.
A15: C6 | B15: Cart, checkout and order lifecycle | C15: ='Effort - Mobile & IPRS'!G22 -> 46 | D15: Phase 2 | E15: =IF(D15="Phase 1",C15,0) -> 0 | F15: Mobile app deferred; the portal carries commerce in phase 1.
A16: C7 | B16: Payment: gateway SDK, UPI, cards, netbanking, PO approval | C16: ='Effort - Mobile & IPRS'!G23 -> 31 | D16: Phase 2 | E16: =IF(D16="Phase 1",C16,0) -> 0 | F16: Mobile app deferred; the portal carries commerce in phase 1.
A17: C8 | B17: Notifications: push, SMS, email, preference centre | C17: ='Effort - Mobile & IPRS'!G24 -> 19 | D17: Phase 2 | E17: =IF(D17="Phase 1",C17,0) -> 0 | F17: Mobile app deferred; the portal carries commerce in phase 1.
A18: C9 | B18: Feedback, support ticketing, FAQ, self-help | C18: ='Effort - Mobile & IPRS'!G25 -> 21 | D18: Phase 2 | E18: =IF(D18="Phase 1",C18,0) -> 0 | F18: Mobile app deferred; the portal carries commerce in phase 1.
A19: C10 | B19: Accessibility engineering to WCAG 2.1 AA, both platforms | C19: ='Effort - Mobile & IPRS'!G26 -> 26 | D19: Phase 2 | E19: =IF(D19="Phase 1",C19,0) -> 0 | F19: Mobile app deferred; the portal carries commerce in phase 1.
A20: C11 | B20: GIGW 3.0 mobile conformance and CERT-In cyber chapter | C20: ='Effort - Mobile & IPRS'!G27 -> 21 | D20: Phase 2 | E20: =IF(D20="Phase 1",C20,0) -> 0 | F20: Mobile app deferred; the portal carries commerce in phase 1.
A21: C12 | B21: App hardening: pinning, root detection, obfuscation, cache | C21: ='Effort - Mobile & IPRS'!G28 -> 21 | D21: Phase 2 | E21: =IF(D21="Phase 1",C21,0) -> 0 | F21: Mobile app deferred; the portal carries commerce in phase 1.
A22: C13 | B22: Store submission, release engineering, phased rollout | C22: ='Effort - Mobile & IPRS'!G29 -> 13 | D22: Phase 2 | E22: =IF(D22="Phase 1",C22,0) -> 0 | F22: Mobile app deferred; the portal carries commerce in phase 1.
A23: D1 | B23: Console foundation, four-role RBAC, audit instrumentation | C23: ='Effort - Mobile & IPRS'!G33 -> 35 | D23: Phase 1 | E23: =IF(D23="Phase 1",C23,0) -> 35
A24: D2 | B24: IPRS Admin: lots, batches, expiry, stock signals | C24: ='Effort - Mobile & IPRS'!G34 -> 33 | D24: Phase 1 | E24: =IF(D24="Phase 1",C24,0) -> 33
A25: D3 | B25: CoA and Lot Validity Statement generation engine | C25: ='Effort - Mobile & IPRS'!G35 -> 25 | D25: Phase 1 | E25: =IF(D25="Phase 1",C25,0) -> 25
A26: D4 | B26: Price-tier engine and government-organisation assignment | C26: ='Effort - Mobile & IPRS'!G36 -> 25 | D26: Phase 1 | E26: =IF(D26="Phase 1",C26,0) -> 25
A27: D5 | B27: Verification workflow: document review, approval, revalidation | C27: ='Effort - Mobile & IPRS'!G37 -> 27 | D27: Phase 1 | E27: =IF(D27="Phase 1",C27,0) -> 27
A28: D6 | B28: Dispatch Admin: scheduling, couriers, slips, tracking | C28: ='Effort - Mobile & IPRS'!G38 -> 41 | D28: Phase 1 | E28: =IF(D28="Phase 1",C28,0) -> 41
A29: D7 | B29: Order management console, refunds, cancellations | C29: ='Effort - Mobile & IPRS'!G39 -> 26 | D29: Phase 1 | E29: =IF(D29="Phase 1",C29,0) -> 26
A30: D8 | B30: User management and registration logs | C30: ='Effort - Mobile & IPRS'!G40 -> 16 | D30: Phase 1 | E30: =IF(D30="Phase 1",C30,0) -> 16
A31: D9 | B31: Notification console: templates, scheduling, delivery reports | C31: ='Effort - Mobile & IPRS'!G41 -> 21 | D31: Phase 1 | E31: =IF(D31="Phase 1",C31,0) -> 21
A32: D10 | B32: Feedback and ticket management, escalation | C32: ='Effort - Mobile & IPRS'!G42 -> 21 | D32: Phase 1 | E32: =IF(D32="Phase 1",C32,0) -> 21
A33: D11 | B33: Search analytics and demand reporting | C33: ='Effort - Mobile & IPRS'!G43 -> 23 | D33: Phase 1 | E33: =IF(D33="Phase 1",C33,0) -> 23
A34: D12 | B34: Reporting engine, role-scoped, PDF/Excel, scheduling | C34: ='Effort - Mobile & IPRS'!G44 -> 36 | D34: Phase 1 | E34: =IF(D34="Phase 1",C34,0) -> 36
A35: D13 | B35: Immutable audit log: append-only, hash-chained, exportable | C35: ='Effort - Mobile & IPRS'!G45 -> 26 | D35: Phase 1 | E35: =IF(D35="Phase 1",C35,0) -> 26
A36: E1 | B36: API platform: catalogue, lot, order, identity services | C36: ='Effort - Mobile & IPRS'!G49 -> 72 | D36: Phase 1 | E36: =IF(D36="Phase 1",C36,0) -> 72
A37: E2 | B37: Document generation: CoA, LVS, GST invoice, dispatch slip | C37: ='Effort - Mobile & IPRS'!G50 -> 31 | D37: Phase 1 | E37: =IF(D37="Phase 1",C37,0) -> 31
A38: E3 | B38: Payment gateway and settlement reconciliation | C38: ='Effort - Mobile & IPRS'!G51 -> 13 | D38: Phase 1 | E38: =IF(D38="Phase 1",C38,0) -> 13
A39: E4 | B39: Courier API integration and tracking webhooks | C39: ='Effort - Mobile & IPRS'!G52 -> 16 | D39: Phase 1 | E39: =IF(D39="Phase 1",C39,0) -> 16
A40: E5 | B40: Tally / ERP posting, reconciliation, GST e-invoicing (IRN) | C40: ='Effort - Mobile & IPRS'!G53 -> 21 | D40: Phase 1 | E40: =IF(D40="Phase 1",C40,0) -> 21
A41: E6 | B41: Pin-code serviceability API | C41: ='Effort - Mobile & IPRS'!G54 -> 5 | D41: Phase 1 | E41: =IF(D41="Phase 1",C41,0) -> 5
A42: E7 | B42: SMS and email integration incl. TRAI DLT registration | C42: ='Effort - Mobile & IPRS'!G55 -> 13 | D42: Phase 1 | E42: =IF(D42="Phase 1",C42,0) -> 13
A43: E8 | B43: IP Online federation and SSO | C43: ='Effort - Mobile & IPRS'!G56 -> 26 | D43: Phase 1 | E43: =IF(D43="Phase 1",C43,0) -> 26
A44: E9 | B44: LIMS / QC ingest to source Certificate of Analysis data | C44: ='Effort - Mobile & IPRS'!G57 -> 25 | D44: Phase 1 | E44: =IF(D44="Phase 1",C44,0) -> 25
A45: E10 | B45: Five-lot history backfill and lot data structuring | C45: ='Effort - Mobile & IPRS'!G58 -> 15 | D45: Phase 1 | E45: =IF(D45="Phase 1",C45,0) -> 15
A46: E11 | B46: Infrastructure, IaC, environments, CI/CD, observability, DR | C46: ='Effort - Mobile & IPRS'!G59 -> 46 | D46: Phase 1 | E46: =IF(D46="Phase 1",C46,0) -> 46
A47: E12 | B47: Security engineering, CERT-In audit support, VAPT | C47: ='Effort - Mobile & IPRS'!G60 -> 31 | D47: Phase 1 | E47: =IF(D47="Phase 1",C47,0) -> 31
A48: H1 | B48: Discovery, workshops, information architecture, sitemap | C48: ='Effort - Website'!G6 -> 29 | D48: Phase 1 | E48: =IF(D48="Phase 1",C48,0) -> 29
A49: H2 | B49: Content audit and migration plan | C49: ='Effort - Website'!G7 -> 14 | D49: Phase 1 | E49: =IF(D49="Phase 1",C49,0) -> 14
A50: I1 | B50: GIGW 3.0 / DBIM design system, bilingual type and grid | C50: ='Effort - Website'!G11 -> 31 | D50: Phase 1 | E50: =IF(D50="Phase 1",C50,0) -> 31
A51: I2 | B51: Template design, ~28 page templates | C51: ='Effort - Website'!G12 -> 43 | D51: Phase 1 | E51: =IF(D51="Phase 1",C51,0) -> 43
A52: I3 | B52: Commerce and account journey design | C52: ='Effort - Website'!G13 -> 17 | D52: Phase 1 | E52: =IF(D52="Phase 1",C52,0) -> 17
A53: J1 | B53: CMS platform setup, hardening, environments | C53: ='Effort - Website'!G17 -> 25 | D53: Phase 1 | E53: =IF(D53="Phase 1",C53,0) -> 25
A54: J2 | B54: RBAC and editorial approval workflow | C54: ='Effort - Website'!G18 -> 21 | D54: Phase 1 | E54: =IF(D54="Phase 1",C54,0) -> 21
A55: J3 | B55: Bilingual WYSIWYG authoring, spellcheck, media embed | C55: ='Effort - Website'!G19 -> 13 | D55: Phase 1 | E55: =IF(D55="Phase 1",C55,0) -> 13
A56: J4 | B56: Scheduling, auto-publish, auto-expire, expiry alerts | C56: ='Effort - Website'!G20 -> 11 | D56: Phase 1 | E56: =IF(D56="Phase 1",C56,0) -> 11
A57: J5 | B57: Backup, versioning, rollback, version compare | C57: ='Effort - Website'!G21 -> 13 | D57: Phase 1 | E57: =IF(D57="Phase 1",C57,0) -> 13
A58: J6 | B58: Immutable CMS audit trail and exportable logs | C58: ='Effort - Website'!G22 -> 19 | D58: Phase 1 | E58: =IF(D58="Phase 1",C58,0) -> 19
A59: J7 | B59: Archival engine: rules, retention, archive section, labelling | C59: ='Effort - Website'!G23 -> 21 | D59: Phase 1 | E59: =IF(D59="Phase 1",C59,0) -> 21
A60: K1 | B60: Video platform integration, player, captions, transcripts | C60: ='Effort - Website'!G27 -> 29 | D60: Phase 1 | E60: =IF(D60="Phase 1",C60,0) -> 29
A61: K2 | B61: Image wizard: gallery, resize, alt text, bulk upload | C61: ='Effort - Website'!G28 -> 17 | D61: Phase 1 | E61: =IF(D61="Phase 1",C61,0) -> 17
A62: K3 | B62: Document management: versioning, indexing, secure download | C62: ='Effort - Website'!G29 -> 25 | D62: Phase 1 | E62: =IF(D62="Phase 1",C62,0) -> 25
A63: K4 | B63: Event calendar, registration, reminders, archive | C63: ='Effort - Website'!G30 -> 31 | D63: Phase 1 | E63: =IF(D63="Phase 1",C63,0) -> 31
A64: K5 | B64: FAQ and glossary modules | C64: ='Effort - Website'!G31 -> 19 | D64: Phase 1 | E64: =IF(D64="Phase 1",C64,0) -> 19
A65: K6 | B65: Polls and visitor survey with analytics | C65: ='Effort - Website'!G32 -> 17 | D65: Phase 2 | E65: =IF(D65="Phase 1",C65,0) -> 0 | F65: Community features deferred.
A66: K7 | B66: Public forum: threads, moderation, reputation, redressal | C66: ='Effort - Website'!G33 -> 46 | D66: Phase 2 | E66: =IF(D66="Phase 1",C66,0) -> 0 | F66: Community features deferred.
A67: K8 | B67: Recruitment form, tracking, export, HR dashboard | C67: ='Effort - Website'!G34 -> 25 | D67: Phase 1 | E67: =IF(D67="Phase 1",C67,0) -> 25
A68: L1 | B68: Templates, mega menu, breadcrumbs, sticky nav, cards | C68: ='Effort - Website'!G38 -> 51 | D68: Phase 1 | E68: =IF(D68="Phase 1",C68,0) -> 51
A69: L2 | B69: Personalisation widgets, quick tiles, one-click downloads | C69: ='Effort - Website'!G39 -> 19 | D69: Phase 2 | E69: =IF(D69="Phase 1",C69,0) -> 0 | F69: Personalisation deferred.
A70: L3 | B70: Bilingual framework and language toggle | C70: ='Effort - Website'!G40 -> 16 | D70: Phase 1 | E70: =IF(D70="Phase 1",C70,0) -> 16
A71: L4 | B71: Accessibility engineering to WCAG 2.1 AA | C71: ='Effort - Website'!G41 -> 39 | D71: Phase 1 | E71: =IF(D71="Phase 1",C71,0) -> 39
A72: M1 | B72: Search platform, indexing, multilingual facets, relevance | C72: ='Effort - Website'!G45 -> 33 | D72: Phase 1 | E72: =IF(D72="Phase 1",C72,0) -> 33
A73: M2 | B73: Semantic / vector search and recommendations | C73: ='Effort - Website'!G46 -> 29 | D73: Phase 2 | E73: =IF(D73="Phase 1",C73,0) -> 0 | F73: AI layer deferred; keyword and facet search ship first.
A74: M3 | B74: Voice search and text-to-speech / speech-to-text | C74: ='Effort - Website'!G47 -> 21 | D74: Phase 2 | E74: =IF(D74="Phase 1",C74,0) -> 0 | F74: AI layer deferred; keyword and facet search ship first.
A75: M4 | B75: Chatbot assistant: retrieval, guardrails, escalation | C75: ='Effort - Website'!G48 -> 47 | D75: Phase 2 | E75: =IF(D75="Phase 1",C75,0) -> 0 | F75: AI layer deferred; keyword and facet search ship first.
A76: M5 | B76: AI auto-tagging and document classification | C76: ='Effort - Website'!G49 -> 25 | D76: Phase 2 | E76: =IF(D76="Phase 1",C76,0) -> 0 | F76: AI layer deferred; keyword and facet search ship first.
A77: M6 | B77: AI moderation: spam, misuse, fraud detection | C77: ='Effort - Website'!G50 -> 19 | D77: Phase 2 | E77: =IF(D77="Phase 1",C77,0) -> 0 | F77: AI layer deferred; keyword and facet search ship first.
A78: M7 | B78: AI governance: evaluation harness, accuracy testing, HITL | C78: ='Effort - Website'!G51 -> 19 | D78: Phase 2 | E78: =IF(D78="Phase 1",C78,0) -> 0 | F78: AI layer deferred; keyword and facet search ship first.
A79: N1 | B79: Catalogue, categories, filters, bulk upload, versioning | C79: ='Effort - Website'!G55 -> 31 | D79: Phase 1 | E79: =IF(D79="Phase 1",C79,0) -> 31
A80: N2 | B80: Catalogue data onboarding: 1,341 SKUs, lots, two price tiers | C80: ='Effort - Website'!G56 -> 26 | D80: Phase 1 | E80: =IF(D80="Phase 1",C80,0) -> 26
A81: N3 | B81: Cart, checkout, address, shipping, tax, persistence, reorder | C81: ='Effort - Website'!G57 -> 36 | D81: Phase 1 | E81: =IF(D81="Phase 1",C81,0) -> 36
A82: N4 | B82: Payment gateway, multi-currency, retries, reconciliation | C82: ='Effort - Website'!G58 -> 21 | D82: Phase 1 | E82: =IF(D82="Phase 1",C82,0) -> 21
A83: N5 | B83: Order management, notifications, refunds, reports | C83: ='Effort - Website'!G59 -> 31 | D83: Phase 1 | E83: =IF(D83="Phase 1",C83,0) -> 31
A84: N6 | B84: Customer accounts, history, invoices, subscriptions, tracking | C84: ='Effort - Website'!G60 -> 26 | D84: Phase 1 | E84: =IF(D84="Phase 1",C84,0) -> 26
A85: N7 | B85: Promotions, discount codes, scheduling, banners | C85: ='Effort - Website'!G61 -> 19 | D85: Phase 1 | E85: =IF(D85="Phase 1",C85,0) -> 19
A86: N8 | B86: Sales analytics, funnels, dashboards | C86: ='Effort - Website'!G62 -> 23 | D86: Phase 1 | E86: =IF(D86="Phase 1",C86,0) -> 23
A87: N9 | B87: OpenCart data migration: products, customers, order history | C87: ='Effort - Website'!G63 -> 36 | D87: Phase 1 | E87: =IF(D87="Phase 1",C87,0) -> 36
A88: O1 | B88: Visitor analytics, event and journey tracking | C88: ='Effort - Website'!G67 -> 21 | D88: Phase 1 | E88: =IF(D88="Phase 1",C88,0) -> 21
A89: O2 | B89: Heatmaps, funnel and behavioural analytics | C89: ='Effort - Website'!G68 -> 17 | D89: Phase 1 | E89: =IF(D89="Phase 1",C89,0) -> 17
A90: O3 | B90: MIS dashboard: widgets, drill-down, scheduled reports | C90: ='Effort - Website'!G69 -> 36 | D90: Phase 1 | E90: =IF(D90="Phase 1",C90,0) -> 36
A91: O4 | B91: DPDP consent management and Consent Manager integration | C91: ='Effort - Website'!G70 -> 29 | D91: Phase 1 | E91: =IF(D91="Phase 1",C91,0) -> 29
A92: O5 | B92: Transactional and promotional SMS/email, bilingual, analytics | C92: ='Effort - Website'!G71 -> 31 | D92: Phase 1 | E92: =IF(D92="Phase 1",C92,0) -> 31
A93: O6 | B93: IP Online / PvPI integration and SSO across IPC portals | C93: ='Effort - Website'!G72 -> 36 | D93: Phase 1 | E93: =IF(D93="Phase 1",C93,0) -> 36
A94: P1 | B94: Migration tooling and mapping, Joomla to target | C94: ='Effort - Website'!G76 -> 25 | D94: Phase 1 | E94: =IF(D94="Phase 1",C94,0) -> 25
A95: P2 | B95: Article and document migration, ~1,500 items, plus QA | C95: ='Effort - Website'!G77 -> 36 | D95: Phase 1 | E95: =IF(D95="Phase 1",C95,0) -> 36
A96: P3 | B96: Hindi coverage completion and bilingual QA | C96: ='Effort - Website'!G78 -> 16 | D96: Phase 1 | E96: =IF(D96="Phase 1",C96,0) -> 16
A97: P4 | B97: URL redirect mapping and SEO preservation | C97: ='Effort - Website'!G79 -> 13 | D97: Phase 1 | E97: =IF(D97="Phase 1",C97,0) -> 13
A98: Q1 | B98: NIC / MeitY hosting provisioning, IaC, environments | C98: ='Effort - Website'!G83 -> 31 | D98: Phase 1 | E98: =IF(D98="Phase 1",C98,0) -> 31
A99: Q2 | B99: DR site, replication, failover, drill runbooks | C99: ='Effort - Website'!G84 -> 27 | D99: Phase 1 | E99: =IF(D99="Phase 1",C99,0) -> 27
A100: Q3 | B100: Monitoring, IDPS, alerting, SOC handover | C100: ='Effort - Website'!G85 -> 19 | D100: Phase 1 | E100: =IF(D100="Phase 1",C100,0) -> 19
A101: Q4 | B101: Security engineering and two VAPT cycles | C101: ='Effort - Website'!G86 -> 31 | D101: Phase 1 | E101: =IF(D101="Phase 1",C101,0) -> 31
...

Sheet Scenario D Model
A1: Scenario D — Replatform, Modelled
A2: Replaces the 0.58x multiplier. Every module carries a disposition factor: what fraction survives if the live Joomla and OpenCart estate is upgraded rather than replaced.
A4: Ref | B4: Module | C4: Expected (PD) | D4: Factor (0–1, dimensionless) | E4: Retained (PD) | F4: Why the factor is not 1.00
A5: A1 | B5: Requirements elaboration, SRS and traceability matrix | C5: ='Effort - Mobile & IPRS'!G6 -> 33 | D5: 1 | E5: =ROUND(C5*D5,0) -> 33
A6: A2 | B6: Solution architecture, domain model, integration contracts | C6: ='Effort - Mobile & IPRS'!G7 -> 29 | D6: 1 | E6: =ROUND(C6*D6,0) -> 29
A7: B1 | B7: Design system and accessible mobile UI kit | C7: ='Effort - Mobile & IPRS'!G11 -> 27 | D7: 1 | E7: =ROUND(C7*D7,0) -> 27
A8: B2 | B8: Mobile screen design, ~55 screens, two platforms | C8: ='Effort - Mobile & IPRS'!G12 -> 37 | D8: 1 | E8: =ROUND(C8*D8,0) -> 37
A9: B3 | B9: Admin console design, ~40 screens, four roles | C9: ='Effort - Mobile & IPRS'!G13 -> 29 | D9: 1 | E9: =ROUND(C9*D9,0) -> 29
A10: C1 | B10: App foundation, navigation, state, mobile CI/CD | C10: ='Effort - Mobile & IPRS'!G17 -> 35 | D10: 1 | E10: =ROUND(C10*D10,0) -> 35
A11: C2 | B11: Registration, OTP, biometric, MFA, institutional onboarding | C11: ='Effort - Mobile & IPRS'!G18 -> 31 | D11: 1 | E11: =ROUND(C11*D11,0) -> 31
A12: C3 | B12: IPRS/IMPRS catalogue, lot detail, CoA / LVS / SDS viewer | C12: ='Effort - Mobile & IPRS'!G19 -> 41 | D12: 1 | E12: =ROUND(C12*D12,0) -> 41
A13: C4 | B13: Publications and subscriptions, edition history, renewals | C13: ='Effort - Mobile & IPRS'!G20 -> 23 | D13: 1 | E13: =ROUND(C13*D13,0) -> 23
A14: C5 | B14: Smart search, filters, predictive, voice, recommendations | C14: ='Effort - Mobile & IPRS'!G21 -> 31 | D14: 1 | E14: =ROUND(C14*D14,0) -> 31
A15: C6 | B15: Cart, checkout and order lifecycle | C15: ='Effort - Mobile & IPRS'!G22 -> 46 | D15: 1 | E15: =ROUND(C15*D15,0) -> 46
A16: C7 | B16: Payment: gateway SDK, UPI, cards, netbanking, PO approval | C16: ='Effort - Mobile & IPRS'!G23 -> 31 | D16: 1 | E16: =ROUND(C16*D16,0) -> 31
A17: C8 | B17: Notifications: push, SMS, email, preference centre | C17: ='Effort - Mobile & IPRS'!G24 -> 19 | D17: 1 | E17: =ROUND(C17*D17,0) -> 19
A18: C9 | B18: Feedback, support ticketing, FAQ, self-help | C18: ='Effort - Mobile & IPRS'!G25 -> 21 | D18: 1 | E18: =ROUND(C18*D18,0) -> 21
A19: C10 | B19: Accessibility engineering to WCAG 2.1 AA, both platforms | C19: ='Effort - Mobile & IPRS'!G26 -> 26 | D19: 1 | E19: =ROUND(C19*D19,0) -> 26
A20: C11 | B20: GIGW 3.0 mobile conformance and CERT-In cyber chapter | C20: ='Effort - Mobile & IPRS'!G27 -> 21 | D20: 1 | E20: =ROUND(C20*D20,0) -> 21
A21: C12 | B21: App hardening: pinning, root detection, obfuscation, cache | C21: ='Effort - Mobile & IPRS'!G28 -> 21 | D21: 1 | E21: =ROUND(C21*D21,0) -> 21
A22: C13 | B22: Store submission, release engineering, phased rollout | C22: ='Effort - Mobile & IPRS'!G29 -> 13 | D22: 1 | E22: =ROUND(C22*D22,0) -> 13
A23: D1 | B23: Console foundation, four-role RBAC, audit instrumentation | C23: ='Effort - Mobile & IPRS'!G33 -> 35 | D23: 1 | E23: =ROUND(C23*D23,0) -> 35
A24: D2 | B24: IPRS Admin: lots, batches, expiry, stock signals | C24: ='Effort - Mobile & IPRS'!G34 -> 33 | D24: 1 | E24: =ROUND(C24*D24,0) -> 33
A25: D3 | B25: CoA and Lot Validity Statement generation engine | C25: ='Effort - Mobile & IPRS'!G35 -> 25 | D25: 1 | E25: =ROUND(C25*D25,0) -> 25
A26: D4 | B26: Price-tier engine and government-organisation assignment | C26: ='Effort - Mobile & IPRS'!G36 -> 25 | D26: 1 | E26: =ROUND(C26*D26,0) -> 25
A27: D5 | B27: Verification workflow: document review, approval, revalidation | C27: ='Effort - Mobile & IPRS'!G37 -> 27 | D27: 1 | E27: =ROUND(C27*D27,0) -> 27
A28: D6 | B28: Dispatch Admin: scheduling, couriers, slips, tracking | C28: ='Effort - Mobile & IPRS'!G38 -> 41 | D28: 1 | E28: =ROUND(C28*D28,0) -> 41
A29: D7 | B29: Order management console, refunds, cancellations | C29: ='Effort - Mobile & IPRS'!G39 -> 26 | D29: 1 | E29: =ROUND(C29*D29,0) -> 26
A30: D8 | B30: User management and registration logs | C30: ='Effort - Mobile & IPRS'!G40 -> 16 | D30: 1 | E30: =ROUND(C30*D30,0) -> 16
A31: D9 | B31: Notification console: templates, scheduling, delivery reports | C31: ='Effort - Mobile & IPRS'!G41 -> 21 | D31: 1 | E31: =ROUND(C31*D31,0) -> 21
A32: D10 | B32: Feedback and ticket management, escalation | C32: ='Effort - Mobile & IPRS'!G42 -> 21 | D32: 1 | E32: =ROUND(C32*D32,0) -> 21
A33: D11 | B33: Search analytics and demand reporting | C33: ='Effort - Mobile & IPRS'!G43 -> 23 | D33: 1 | E33: =ROUND(C33*D33,0) -> 23
A34: D12 | B34: Reporting engine, role-scoped, PDF/Excel, scheduling | C34: ='Effort - Mobile & IPRS'!G44 -> 36 | D34: 1 | E34: =ROUND(C34*D34,0) -> 36
A35: D13 | B35: Immutable audit log: append-only, hash-chained, exportable | C35: ='Effort - Mobile & IPRS'!G45 -> 26 | D35: 1 | E35: =ROUND(C35*D35,0) -> 26
A36: E1 | B36: API platform: catalogue, lot, order, identity services | C36: ='Effort - Mobile & IPRS'!G49 -> 72 | D36: 1 | E36: =ROUND(C36*D36,0) -> 72
A37: E2 | B37: Document generation: CoA, LVS, GST invoice, dispatch slip | C37: ='Effort - Mobile & IPRS'!G50 -> 31 | D37: 1 | E37: =ROUND(C37*D37,0) -> 31
A38: E3 | B38: Payment gateway and settlement reconciliation | C38: ='Effort - Mobile & IPRS'!G51 -> 13 | D38: 1 | E38: =ROUND(C38*D38,0) -> 13
A39: E4 | B39: Courier API integration and tracking webhooks | C39: ='Effort - Mobile & IPRS'!G52 -> 16 | D39: 1 | E39: =ROUND(C39*D39,0) -> 16
A40: E5 | B40: Tally / ERP posting, reconciliation, GST e-invoicing (IRN) | C40: ='Effort - Mobile & IPRS'!G53 -> 21 | D40: 1 | E40: =ROUND(C40*D40,0) -> 21
A41: E6 | B41: Pin-code serviceability API | C41: ='Effort - Mobile & IPRS'!G54 -> 5 | D41: 1 | E41: =ROUND(C41*D41,0) -> 5
A42: E7 | B42: SMS and email integration incl. TRAI DLT registration | C42: ='Effort - Mobile & IPRS'!G55 -> 13 | D42: 1 | E42: =ROUND(C42*D42,0) -> 13
A43: E8 | B43: IP Online federation and SSO | C43: ='Effort - Mobile & IPRS'!G56 -> 26 | D43: 1 | E43: =ROUND(C43*D43,0) -> 26
A44: E9 | B44: LIMS / QC ingest to source Certificate of Analysis data | C44: ='Effort - Mobile & IPRS'!G57 -> 25 | D44: 1 | E44: =ROUND(C44*D44,0) -> 25
A45: E10 | B45: Five-lot history backfill and lot data structuring | C45: ='Effort - Mobile & IPRS'!G58 -> 15 | D45: 1 | E45: =ROUND(C45*D45,0) -> 15
A46: E11 | B46: Infrastructure, IaC, environments, CI/CD, observability, DR | C46: ='Effort - Mobile & IPRS'!G59 -> 46 | D46: 1 | E46: =ROUND(C46*D46,0) -> 46
A47: E12 | B47: Security engineering, CERT-In audit support, VAPT | C47: ='Effort - Mobile & IPRS'!G60 -> 31 | D47: 1 | E47: =ROUND(C47*D47,0) -> 31
A48: H1 | B48: Discovery, workshops, information architecture, sitemap | C48: ='Effort - Website'!G6 -> 29 | D48: 1 | E48: =ROUND(C48*D48,0) -> 29
A49: H2 | B49: Content audit and migration plan | C49: ='Effort - Website'!G7 -> 14 | D49: 0.5 | E49: =ROUND(C49*D49,0) -> 7 | F49: Existing platform covers part of this.
A50: I1 | B50: GIGW 3.0 / DBIM design system, bilingual type and grid | C50: ='Effort - Website'!G11 -> 31 | D50: 1 | E50: =ROUND(C50*D50,0) -> 31
A51: I2 | B51: Template design, ~28 page templates | C51: ='Effort - Website'!G12 -> 43 | D51: 1 | E51: =ROUND(C51*D51,0) -> 43 | F51: Full redesign is the point of the exercise and survives intact.
A52: I3 | B52: Commerce and account journey design | C52: ='Effort - Website'!G13 -> 17 | D52: 1 | E52: =ROUND(C52*D52,0) -> 17
A53: J1 | B53: CMS platform setup, hardening, environments | C53: ='Effort - Website'!G17 -> 25 | D53: 0.45 | E53: =ROUND(C53*D53,0) -> 11 | F53: Joomla is upgraded in place rather than replaced by a new CMS.
A54: J2 | B54: RBAC and editorial approval workflow | C54: ='Effort - Website'!G18 -> 21 | D54: 0.7 | E54: =ROUND(C54*D54,0) -> 15 | F54: Existing platform covers part of this.
A55: J3 | B55: Bilingual WYSIWYG authoring, spellcheck, media embed | C55: ='Effort - Website'!G19 -> 13 | D55: 0.7 | E55: =ROUND(C55*D55,0) -> 9 | F55: Existing platform covers part of this.
A56: J4 | B56: Scheduling, auto-publish, auto-expire, expiry alerts | C56: ='Effort - Website'!G20 -> 11 | D56: 0.7 | E56: =ROUND(C56*D56,0) -> 8 | F56: Existing platform covers part of this.
A57: J5 | B57: Backup, versioning, rollback, version compare | C57: ='Effort - Website'!G21 -> 13 | D57: 0.7 | E57: =ROUND(C57*D57,0) -> 9 | F57: Existing platform covers part of this.
A58: J6 | B58: Immutable CMS audit trail and exportable logs | C58: ='Effort - Website'!G22 -> 19 | D58: 0.85 | E58: =ROUND(C58*D58,0) -> 16 | F58: Existing platform covers part of this.
A59: J7 | B59: Archival engine: rules, retention, archive section, labelling | C59: ='Effort - Website'!G23 -> 21 | D59: 0.7 | E59: =ROUND(C59*D59,0) -> 15 | F59: Existing platform covers part of this.
A60: K1 | B60: Video platform integration, player, captions, transcripts | C60: ='Effort - Website'!G27 -> 29 | D60: 1 | E60: =ROUND(C60*D60,0) -> 29
A61: K2 | B61: Image wizard: gallery, resize, alt text, bulk upload | C61: ='Effort - Website'!G28 -> 17 | D61: 0.6 | E61: =ROUND(C61*D61,0) -> 10 | F61: Existing platform covers part of this.
A62: K3 | B62: Document management: versioning, indexing, secure download | C62: ='Effort - Website'!G29 -> 25 | D62: 0.75 | E62: =ROUND(C62*D62,0) -> 19 | F62: Existing platform covers part of this.
A63: K4 | B63: Event calendar, registration, reminders, archive | C63: ='Effort - Website'!G30 -> 31 | D63: 1 | E63: =ROUND(C63*D63,0) -> 31
A64: K5 | B64: FAQ and glossary modules | C64: ='Effort - Website'!G31 -> 19 | D64: 0.6 | E64: =ROUND(C64*D64,0) -> 11 | F64: Existing platform covers part of this.
A65: K6 | B65: Polls and visitor survey with analytics | C65: ='Effort - Website'!G32 -> 17 | D65: 1 | E65: =ROUND(C65*D65,0) -> 17
A66: K7 | B66: Public forum: threads, moderation, reputation, redressal | C66: ='Effort - Website'!G33 -> 46 | D66: 1 | E66: =ROUND(C66*D66,0) -> 46
A67: K8 | B67: Recruitment form, tracking, export, HR dashboard | C67: ='Effort - Website'!G34 -> 25 | D67: 0.55 | E67: =ROUND(C67*D67,0) -> 14 | F67: Existing platform covers part of this.
A68: L1 | B68: Templates, mega menu, breadcrumbs, sticky nav, cards | C68: ='Effort - Website'!G38 -> 51 | D68: 0.85 | E68: =ROUND(C68*D68,0) -> 43 | F68: Existing platform covers part of this.
A69: L2 | B69: Personalisation widgets, quick tiles, one-click downloads | C69: ='Effort - Website'!G39 -> 19 | D69: 1 | E69: =ROUND(C69*D69,0) -> 19
A70: L3 | B70: Bilingual framework and language toggle | C70: ='Effort - Website'!G40 -> 16 | D70: 1 | E70: =ROUND(C70*D70,0) -> 16
A71: L4 | B71: Accessibility engineering to WCAG 2.1 AA | C71: ='Effort - Website'!G41 -> 39 | D71: 1 | E71: =ROUND(C71*D71,0) -> 39
A72: M1 | B72: Search platform, indexing, multilingual facets, relevance | C72: ='Effort - Website'!G45 -> 33 | D72: 1 | E72: =ROUND(C72*D72,0) -> 33
A73: M2 | B73: Semantic / vector search and recommendations | C73: ='Effort - Website'!G46 -> 29 | D73: 1 | E73: =ROUND(C73*D73,0) -> 29
A74: M3 | B74: Voice search and text-to-speech / speech-to-text | C74: ='Effort - Website'!G47 -> 21 | D74: 1 | E74: =ROUND(C74*D74,0) -> 21
A75: M4 | B75: Chatbot assistant: retrieval, guardrails, escalation | C75: ='Effort - Website'!G48 -> 47 | D75: 1 | E75: =ROUND(C75*D75,0) -> 47
A76: M5 | B76: AI auto-tagging and document classification | C76: ='Effort - Website'!G49 -> 25 | D76: 1 | E76: =ROUND(C76*D76,0) -> 25
A77: M6 | B77: AI moderation: spam, misuse, fraud detection | C77: ='Effort - Website'!G50 -> 19 | D77: 1 | E77: =ROUND(C77*D77,0) -> 19
A78: M7 | B78: AI governance: evaluation harness, accuracy testing, HITL | C78: ='Effort - Website'!G51 -> 19 | D78: 1 | E78: =ROUND(C78*D78,0) -> 19
A79: N1 | B79: Catalogue, categories, filters, bulk upload, versioning | C79: ='Effort - Website'!G55 -> 31 | D79: 0.35 | E79: =ROUND(C79*D79,0) -> 11 | F79: OpenCart already holds the catalogue; this becomes remodelling, not building.
A80: N2 | B80: Catalogue data onboarding: 1,341 SKUs, lots, two price tiers | C80: ='Effort - Website'!G56 -> 26 | D80: 1 | E80: =ROUND(C80*D80,0) -> 26
A81: N3 | B81: Cart, checkout, address, shipping, tax, persistence, reorder | C81: ='Effort - Website'!G57 -> 36 | D81: 0.3 | E81: =ROUND(C81*D81,0) -> 11 | F81: Cart and checkout exist and work today.
A82: N4 | B82: Payment gateway, multi-currency, retries, reconciliation | C82: ='Effort - Website'!G58 -> 21 | D82: 0.35 | E82: =ROUND(C82*D82,0) -> 7 | F82: Payment integration is live.
A83: N5 | B83: Order management, notifications, refunds, reports | C83: ='Effort - Website'!G59 -> 31 | D83: 0.4 | E83: =ROUND(C83*D83,0) -> 12 | F83: Order management exists.
A84: N6 | B84: Customer accounts, history, invoices, subscriptions, tracking | C84: ='Effort - Website'!G60 -> 26 | D84: 0.35 | E84: =ROUND(C84*D84,0) -> 9 | F84: Customer accounts exist.
A85: N7 | B85: Promotions, discount codes, scheduling, banners | C85: ='Effort - Website'!G61 -> 19 | D85: 0.3 | E85: =ROUND(C85*D85,0) -> 6 | F85: Existing platform covers part of this.
A86: N8 | B86: Sales analytics, funnels, dashboards | C86: ='Effort - Website'!G62 -> 23 | D86: 0.6 | E86: =ROUND(C86*D86,0) -> 14 | F86: Existing platform covers part of this.
A87: N9 | B87: OpenCart data migration: products, customers, order history | C87: ='Effort - Website'!G63 -> 36 | D87: 0.15 | E87: =ROUND(C87*D87,0) -> 5 | F87: No migration needed if the engine is retained.
A88: O1 | B88: Visitor analytics, event and journey tracking | C88: ='Effort - Website'!G67 -> 21 | D88: 0.7 | E88: =ROUND(C88*D88,0) -> 15 | F88: Existing platform covers part of this.
A89: O2 | B89: Heatmaps, funnel and behavioural analytics | C89: ='Effort - Website'!G68 -> 17 | D89: 0.8 | E89: =ROUND(C89*D89,0) -> 14 | F89: Existing platform covers part of this.
A90: O3 | B90: MIS dashboard: widgets, drill-down, scheduled reports | C90: ='Effort - Website'!G69 -> 36 | D90: 1 | E90: =ROUND(C90*D90,0) -> 36
A91: O4 | B91: DPDP consent management and Consent Manager integration | C91: ='Effort - Website'!G70 -> 29 | D91: 1 | E91: =ROUND(C91*D91,0) -> 29
A92: O5 | B92: Transactional and promotional SMS/email, bilingual, analytics | C92: ='Effort - Website'!G71 -> 31 | D92: 1 | E92: =ROUND(C92*D92,0) -> 31
A93: O6 | B93: IP Online / PvPI integration and SSO across IPC portals | C93: ='Effort - Website'!G72 -> 36 | D93: 1 | E93: =ROUND(C93*D93,0) -> 36
A94: P1 | B94: Migration tooling and mapping, Joomla to target | C94: ='Effort - Website'!G76 -> 25 | D94: 0.25 | E94: =ROUND(C94*D94,0) -> 6 | F94: No CMS change, so no cross-platform migration tooling.
A95: P2 | B95: Article and document migration, ~1,500 items, plus QA | C95: ='Effort - Website'!G77 -> 36 | D95: 0.2 | E95: =ROUND(C95*D95,0) -> 7 | F95: Content stays in place.
A96: P3 | B96: Hindi coverage completion and bilingual QA | C96: ='Effort - Website'!G78 -> 16 | D96: 0.6 | E96: =ROUND(C96*D96,0) -> 10 | F96: Existing platform covers part of this.
A97: P4 | B97: URL redirect mapping and SEO preservation | C97: ='Effort - Website'!G79 -> 13 | D97: 0.2 | E97: =ROUND(C97*D97,0) -> 3 | F97: URLs are largely unchanged, so redirect mapping collapses.
A98: Q1 | B98: NIC / MeitY hosting provisioning, IaC, environments | C98: ='Effort - Website'!G83 -> 31 | D98: 1 | E98: =ROUND(C98*D98,0) -> 31
A99: Q2 | B99: DR site, replication, failover, drill runbooks | C99: ='Effort - Website'!G84 -> 27 | D99: 1 | E99: =ROUND(C99*D99,0) -> 27
A100: Q3 | B100: Monitoring, IDPS, alerting, SOC handover | C100: ='Effort - Website'!G85 -> 19 | D100: 1 | E100: =ROUND(C100*D100,0) -> 19
A101: Q4 | B101: Security engineering and two VAPT cycles | C101: ='Effort - Website'!G86 -> 31 | D101: 1 | E101: =ROUND(C101*D101,0) -> 31
...

Sheet Scenario E Model
A1: Scenario E — IPC Adopts the Product
A2: The scenario the workbook never had. Each IPC module carries a factor: what fraction survives once Lotmark supplies the core.
A4: Ref | B4: IPC module | C4: Expected (PD) | D4: Factor (0–1, dimensionless) | E4: Surviving (PD) | F4: What the product displaces
A5: A1 | B5: Requirements elaboration, SRS and traceability matrix | C5: ='Effort - Mobile & IPRS'!G6 -> 33 | D5: 1 | E5: =ROUND(C5*D5,0) -> 33
A6: A2 | B6: Solution architecture, domain model, integration contracts | C6: ='Effort - Mobile & IPRS'!G7 -> 29 | D6: 1 | E6: =ROUND(C6*D6,0) -> 29
A7: B1 | B7: Design system and accessible mobile UI kit | C7: ='Effort - Mobile & IPRS'!G11 -> 27 | D7: 1 | E7: =ROUND(C7*D7,0) -> 27
A8: B2 | B8: Mobile screen design, ~55 screens, two platforms | C8: ='Effort - Mobile & IPRS'!G12 -> 37 | D8: 1 | E8: =ROUND(C8*D8,0) -> 37
A9: B3 | B9: Admin console design, ~40 screens, four roles | C9: ='Effort - Mobile & IPRS'!G13 -> 29 | D9: 1 | E9: =ROUND(C9*D9,0) -> 29
A10: C1 | B10: App foundation, navigation, state, mobile CI/CD | C10: ='Effort - Mobile & IPRS'!G17 -> 35 | D10: 1 | E10: =ROUND(C10*D10,0) -> 35
A11: C2 | B11: Registration, OTP, biometric, MFA, institutional onboarding | C11: ='Effort - Mobile & IPRS'!G18 -> 31 | D11: 1 | E11: =ROUND(C11*D11,0) -> 31
A12: C3 | B12: IPRS/IMPRS catalogue, lot detail, CoA / LVS / SDS viewer | C12: ='Effort - Mobile & IPRS'!G19 -> 41 | D12: 0.3 | E12: =ROUND(C12*D12,0) -> 12 | F12: Partly supplied by the product.
A13: C4 | B13: Publications and subscriptions, edition history, renewals | C13: ='Effort - Mobile & IPRS'!G20 -> 23 | D13: 0.3 | E13: =ROUND(C13*D13,0) -> 7 | F13: Partly supplied by the product.
A14: C5 | B14: Smart search, filters, predictive, voice, recommendations | C14: ='Effort - Mobile & IPRS'!G21 -> 31 | D14: 1 | E14: =ROUND(C14*D14,0) -> 31
A15: C6 | B15: Cart, checkout and order lifecycle | C15: ='Effort - Mobile & IPRS'!G22 -> 46 | D15: 1 | E15: =ROUND(C15*D15,0) -> 46
A16: C7 | B16: Payment: gateway SDK, UPI, cards, netbanking, PO approval | C16: ='Effort - Mobile & IPRS'!G23 -> 31 | D16: 1 | E16: =ROUND(C16*D16,0) -> 31
A17: C8 | B17: Notifications: push, SMS, email, preference centre | C17: ='Effort - Mobile & IPRS'!G24 -> 19 | D17: 1 | E17: =ROUND(C17*D17,0) -> 19
A18: C9 | B18: Feedback, support ticketing, FAQ, self-help | C18: ='Effort - Mobile & IPRS'!G25 -> 21 | D18: 1 | E18: =ROUND(C18*D18,0) -> 21
A19: C10 | B19: Accessibility engineering to WCAG 2.1 AA, both platforms | C19: ='Effort - Mobile & IPRS'!G26 -> 26 | D19: 1 | E19: =ROUND(C19*D19,0) -> 26
A20: C11 | B20: GIGW 3.0 mobile conformance and CERT-In cyber chapter | C20: ='Effort - Mobile & IPRS'!G27 -> 21 | D20: 1 | E20: =ROUND(C20*D20,0) -> 21
A21: C12 | B21: App hardening: pinning, root detection, obfuscation, cache | C21: ='Effort - Mobile & IPRS'!G28 -> 21 | D21: 1 | E21: =ROUND(C21*D21,0) -> 21
A22: C13 | B22: Store submission, release engineering, phased rollout | C22: ='Effort - Mobile & IPRS'!G29 -> 13 | D22: 1 | E22: =ROUND(C22*D22,0) -> 13
A23: D1 | B23: Console foundation, four-role RBAC, audit instrumentation | C23: ='Effort - Mobile & IPRS'!G33 -> 35 | D23: 0.3 | E23: =ROUND(C23*D23,0) -> 11 | F23: Partly supplied by the product.
A24: D2 | B24: IPRS Admin: lots, batches, expiry, stock signals | C24: ='Effort - Mobile & IPRS'!G34 -> 33 | D24: 0.12 | E24: =ROUND(C24*D24,0) -> 4 | F24: Lot register is core product.
A25: D3 | B25: CoA and Lot Validity Statement generation engine | C25: ='Effort - Mobile & IPRS'!G35 -> 25 | D25: 0.1 | E25: =ROUND(C25*D25,0) -> 3 | F25: Certificate engine is core product.
A26: D4 | B26: Price-tier engine and government-organisation assignment | C26: ='Effort - Mobile & IPRS'!G36 -> 25 | D26: 0.15 | E26: =ROUND(C26*D26,0) -> 4 | F26: Price-tier engine is core product.
A27: D5 | B27: Verification workflow: document review, approval, revalidation | C27: ='Effort - Mobile & IPRS'!G37 -> 27 | D27: 0.15 | E27: =ROUND(C27*D27,0) -> 4 | F27: Verification workflow is core product.
A28: D6 | B28: Dispatch Admin: scheduling, couriers, slips, tracking | C28: ='Effort - Mobile & IPRS'!G38 -> 41 | D28: 0.15 | E28: =ROUND(C28*D28,0) -> 6 | F28: Dispatch and cold chain are core product.
A29: D7 | B29: Order management console, refunds, cancellations | C29: ='Effort - Mobile & IPRS'!G39 -> 26 | D29: 0.12 | E29: =ROUND(C29*D29,0) -> 3 | F29: Partly supplied by the product.
A30: D8 | B30: User management and registration logs | C30: ='Effort - Mobile & IPRS'!G40 -> 16 | D30: 0.3 | E30: =ROUND(C30*D30,0) -> 5 | F30: Partly supplied by the product.
A31: D9 | B31: Notification console: templates, scheduling, delivery reports | C31: ='Effort - Mobile & IPRS'!G41 -> 21 | D31: 0.3 | E31: =ROUND(C31*D31,0) -> 6 | F31: Partly supplied by the product.
A32: D10 | B32: Feedback and ticket management, escalation | C32: ='Effort - Mobile & IPRS'!G42 -> 21 | D32: 0.35 | E32: =ROUND(C32*D32,0) -> 7 | F32: Partly supplied by the product.
A33: D11 | B33: Search analytics and demand reporting | C33: ='Effort - Mobile & IPRS'!G43 -> 23 | D33: 0.2 | E33: =ROUND(C33*D33,0) -> 5 | F33: Partly supplied by the product.
A34: D12 | B34: Reporting engine, role-scoped, PDF/Excel, scheduling | C34: ='Effort - Mobile & IPRS'!G44 -> 36 | D34: 0.2 | E34: =ROUND(C34*D34,0) -> 7 | F34: Partly supplied by the product.
A35: D13 | B35: Immutable audit log: append-only, hash-chained, exportable | C35: ='Effort - Mobile & IPRS'!G45 -> 26 | D35: 0.08 | E35: =ROUND(C35*D35,0) -> 2 | F35: Audit ledger is core product.
A36: E1 | B36: API platform: catalogue, lot, order, identity services | C36: ='Effort - Mobile & IPRS'!G49 -> 72 | D36: 0.35 | E36: =ROUND(C36*D36,0) -> 25 | F36: Product supplies the API platform; tenant integrations remain.
A37: E2 | B37: Document generation: CoA, LVS, GST invoice, dispatch slip | C37: ='Effort - Mobile & IPRS'!G50 -> 31 | D37: 0.12 | E37: =ROUND(C37*D37,0) -> 4 | F37: Partly supplied by the product.
A38: E3 | B38: Payment gateway and settlement reconciliation | C38: ='Effort - Mobile & IPRS'!G51 -> 13 | D38: 0.3 | E38: =ROUND(C38*D38,0) -> 4 | F38: Partly supplied by the product.
A39: E4 | B39: Courier API integration and tracking webhooks | C39: ='Effort - Mobile & IPRS'!G52 -> 16 | D39: 0.3 | E39: =ROUND(C39*D39,0) -> 5 | F39: Partly supplied by the product.
A40: E5 | B40: Tally / ERP posting, reconciliation, GST e-invoicing (IRN) | C40: ='Effort - Mobile & IPRS'!G53 -> 21 | D40: 0.45 | E40: =ROUND(C40*D40,0) -> 9 | F40: Partly supplied by the product.
A41: E6 | B41: Pin-code serviceability API | C41: ='Effort - Mobile & IPRS'!G54 -> 5 | D41: 1 | E41: =ROUND(C41*D41,0) -> 5
A42: E7 | B42: SMS and email integration incl. TRAI DLT registration | C42: ='Effort - Mobile & IPRS'!G55 -> 13 | D42: 0.35 | E42: =ROUND(C42*D42,0) -> 5 | F42: Partly supplied by the product.
A43: E8 | B43: IP Online federation and SSO | C43: ='Effort - Mobile & IPRS'!G56 -> 26 | D43: 1 | E43: =ROUND(C43*D43,0) -> 26
A44: E9 | B44: LIMS / QC ingest to source Certificate of Analysis data | C44: ='Effort - Mobile & IPRS'!G57 -> 25 | D44: 0.2 | E44: =ROUND(C44*D44,0) -> 5 | F44: Product ships a manual QC entry path.
A45: E10 | B45: Five-lot history backfill and lot data structuring | C45: ='Effort - Mobile & IPRS'!G58 -> 15 | D45: 0.15 | E45: =ROUND(C45*D45,0) -> 2 | F45: Partly supplied by the product.
A46: E11 | B46: Infrastructure, IaC, environments, CI/CD, observability, DR | C46: ='Effort - Mobile & IPRS'!G59 -> 46 | D46: 1 | E46: =ROUND(C46*D46,0) -> 46
A47: E12 | B47: Security engineering, CERT-In audit support, VAPT | C47: ='Effort - Mobile & IPRS'!G60 -> 31 | D47: 1 | E47: =ROUND(C47*D47,0) -> 31
A48: H1 | B48: Discovery, workshops, information architecture, sitemap | C48: ='Effort - Website'!G6 -> 29 | D48: 1 | E48: =ROUND(C48*D48,0) -> 29
A49: H2 | B49: Content audit and migration plan | C49: ='Effort - Website'!G7 -> 14 | D49: 1 | E49: =ROUND(C49*D49,0) -> 14
A50: I1 | B50: GIGW 3.0 / DBIM design system, bilingual type and grid | C50: ='Effort - Website'!G11 -> 31 | D50: 1 | E50: =ROUND(C50*D50,0) -> 31
A51: I2 | B51: Template design, ~28 page templates | C51: ='Effort - Website'!G12 -> 43 | D51: 1 | E51: =ROUND(C51*D51,0) -> 43
A52: I3 | B52: Commerce and account journey design | C52: ='Effort - Website'!G13 -> 17 | D52: 1 | E52: =ROUND(C52*D52,0) -> 17
A53: J1 | B53: CMS platform setup, hardening, environments | C53: ='Effort - Website'!G17 -> 25 | D53: 1 | E53: =ROUND(C53*D53,0) -> 25
A54: J2 | B54: RBAC and editorial approval workflow | C54: ='Effort - Website'!G18 -> 21 | D54: 1 | E54: =ROUND(C54*D54,0) -> 21
A55: J3 | B55: Bilingual WYSIWYG authoring, spellcheck, media embed | C55: ='Effort - Website'!G19 -> 13 | D55: 1 | E55: =ROUND(C55*D55,0) -> 13
A56: J4 | B56: Scheduling, auto-publish, auto-expire, expiry alerts | C56: ='Effort - Website'!G20 -> 11 | D56: 1 | E56: =ROUND(C56*D56,0) -> 11
A57: J5 | B57: Backup, versioning, rollback, version compare | C57: ='Effort - Website'!G21 -> 13 | D57: 1 | E57: =ROUND(C57*D57,0) -> 13
A58: J6 | B58: Immutable CMS audit trail and exportable logs | C58: ='Effort - Website'!G22 -> 19 | D58: 1 | E58: =ROUND(C58*D58,0) -> 19
A59: J7 | B59: Archival engine: rules, retention, archive section, labelling | C59: ='Effort - Website'!G23 -> 21 | D59: 1 | E59: =ROUND(C59*D59,0) -> 21
A60: K1 | B60: Video platform integration, player, captions, transcripts | C60: ='Effort - Website'!G27 -> 29 | D60: 1 | E60: =ROUND(C60*D60,0) -> 29
A61: K2 | B61: Image wizard: gallery, resize, alt text, bulk upload | C61: ='Effort - Website'!G28 -> 17 | D61: 1 | E61: =ROUND(C61*D61,0) -> 17
A62: K3 | B62: Document management: versioning, indexing, secure download | C62: ='Effort - Website'!G29 -> 25 | D62: 1 | E62: =ROUND(C62*D62,0) -> 25
A63: K4 | B63: Event calendar, registration, reminders, archive | C63: ='Effort - Website'!G30 -> 31 | D63: 1 | E63: =ROUND(C63*D63,0) -> 31
A64: K5 | B64: FAQ and glossary modules | C64: ='Effort - Website'!G31 -> 19 | D64: 1 | E64: =ROUND(C64*D64,0) -> 19
A65: K6 | B65: Polls and visitor survey with analytics | C65: ='Effort - Website'!G32 -> 17 | D65: 1 | E65: =ROUND(C65*D65,0) -> 17
A66: K7 | B66: Public forum: threads, moderation, reputation, redressal | C66: ='Effort - Website'!G33 -> 46 | D66: 1 | E66: =ROUND(C66*D66,0) -> 46
A67: K8 | B67: Recruitment form, tracking, export, HR dashboard | C67: ='Effort - Website'!G34 -> 25 | D67: 1 | E67: =ROUND(C67*D67,0) -> 25
A68: L1 | B68: Templates, mega menu, breadcrumbs, sticky nav, cards | C68: ='Effort - Website'!G38 -> 51 | D68: 1 | E68: =ROUND(C68*D68,0) -> 51
A69: L2 | B69: Personalisation widgets, quick tiles, one-click downloads | C69: ='Effort - Website'!G39 -> 19 | D69: 1 | E69: =ROUND(C69*D69,0) -> 19
A70: L3 | B70: Bilingual framework and language toggle | C70: ='Effort - Website'!G40 -> 16 | D70: 1 | E70: =ROUND(C70*D70,0) -> 16
A71: L4 | B71: Accessibility engineering to WCAG 2.1 AA | C71: ='Effort - Website'!G41 -> 39 | D71: 1 | E71: =ROUND(C71*D71,0) -> 39
A72: M1 | B72: Search platform, indexing, multilingual facets, relevance | C72: ='Effort - Website'!G45 -> 33 | D72: 1 | E72: =ROUND(C72*D72,0) -> 33
A73: M2 | B73: Semantic / vector search and recommendations | C73: ='Effort - Website'!G46 -> 29 | D73: 1 | E73: =ROUND(C73*D73,0) -> 29
A74: M3 | B74: Voice search and text-to-speech / speech-to-text | C74: ='Effort - Website'!G47 -> 21 | D74: 1 | E74: =ROUND(C74*D74,0) -> 21
A75: M4 | B75: Chatbot assistant: retrieval, guardrails, escalation | C75: ='Effort - Website'!G48 -> 47 | D75: 1 | E75: =ROUND(C75*D75,0) -> 47
A76: M5 | B76: AI auto-tagging and document classification | C76: ='Effort - Website'!G49 -> 25 | D76: 1 | E76: =ROUND(C76*D76,0) -> 25
A77: M6 | B77: AI moderation: spam, misuse, fraud detection | C77: ='Effort - Website'!G50 -> 19 | D77: 1 | E77: =ROUND(C77*D77,0) -> 19
A78: M7 | B78: AI governance: evaluation harness, accuracy testing, HITL | C78: ='Effort - Website'!G51 -> 19 | D78: 1 | E78: =ROUND(C78*D78,0) -> 19
A79: N1 | B79: Catalogue, categories, filters, bulk upload, versioning | C79: ='Effort - Website'!G55 -> 31 | D79: 0.15 | E79: =ROUND(C79*D79,0) -> 5 | F79: Catalogue is core product.
A80: N2 | B80: Catalogue data onboarding: 1,341 SKUs, lots, two price tiers | C80: ='Effort - Website'!G56 -> 26 | D80: 0.55 | E80: =ROUND(C80*D80,0) -> 14 | F80: Data still has to be onboarded, but into a product schema rather than a new build.
A81: N3 | B81: Cart, checkout, address, shipping, tax, persistence, reorder | C81: ='Effort - Website'!G57 -> 36 | D81: 0.15 | E81: =ROUND(C81*D81,0) -> 5 | F81: Cart and checkout are core product.
A82: N4 | B82: Payment gateway, multi-currency, retries, reconciliation | C82: ='Effort - Website'!G58 -> 21 | D82: 0.2 | E82: =ROUND(C82*D82,0) -> 4 | F82: Partly supplied by the product.
A83: N5 | B83: Order management, notifications, refunds, reports | C83: ='Effort - Website'!G59 -> 31 | D83: 0.15 | E83: =ROUND(C83*D83,0) -> 5 | F83: Order management is core product.
A84: N6 | B84: Customer accounts, history, invoices, subscriptions, tracking | C84: ='Effort - Website'!G60 -> 26 | D84: 0.15 | E84: =ROUND(C84*D84,0) -> 4 | F84: Partly supplied by the product.
A85: N7 | B85: Promotions, discount codes, scheduling, banners | C85: ='Effort - Website'!G61 -> 19 | D85: 0.2 | E85: =ROUND(C85*D85,0) -> 4 | F85: Partly supplied by the product.
A86: N8 | B86: Sales analytics, funnels, dashboards | C86: ='Effort - Website'!G62 -> 23 | D86: 0.25 | E86: =ROUND(C86*D86,0) -> 6 | F86: Partly supplied by the product.
A87: N9 | B87: OpenCart data migration: products, customers, order history | C87: ='Effort - Website'!G63 -> 36 | D87: 0.6 | E87: =ROUND(C87*D87,0) -> 22 | F87: OpenCart migration still required, into the product.
A88: O1 | B88: Visitor analytics, event and journey tracking | C88: ='Effort - Website'!G67 -> 21 | D88: 1 | E88: =ROUND(C88*D88,0) -> 21
A89: O2 | B89: Heatmaps, funnel and behavioural analytics | C89: ='Effort - Website'!G68 -> 17 | D89: 1 | E89: =ROUND(C89*D89,0) -> 17
A90: O3 | B90: MIS dashboard: widgets, drill-down, scheduled reports | C90: ='Effort - Website'!G69 -> 36 | D90: 0.4 | E90: =ROUND(C90*D90,0) -> 14 | F90: Partly supplied by the product.
A91: O4 | B91: DPDP consent management and Consent Manager integration | C91: ='Effort - Website'!G70 -> 29 | D91: 1 | E91: =ROUND(C91*D91,0) -> 29
A92: O5 | B92: Transactional and promotional SMS/email, bilingual, analytics | C92: ='Effort - Website'!G71 -> 31 | D92: 1 | E92: =ROUND(C92*D92,0) -> 31
A93: O6 | B93: IP Online / PvPI integration and SSO across IPC portals | C93: ='Effort - Website'!G72 -> 36 | D93: 1 | E93: =ROUND(C93*D93,0) -> 36
A94: P1 | B94: Migration tooling and mapping, Joomla to target | C94: ='Effort - Website'!G76 -> 25 | D94: 1 | E94: =ROUND(C94*D94,0) -> 25
A95: P2 | B95: Article and document migration, ~1,500 items, plus QA | C95: ='Effort - Website'!G77 -> 36 | D95: 1 | E95: =ROUND(C95*D95,0) -> 36
A96: P3 | B96: Hindi coverage completion and bilingual QA | C96: ='Effort - Website'!G78 -> 16 | D96: 1 | E96: =ROUND(C96*D96,0) -> 16
A97: P4 | B97: URL redirect mapping and SEO preservation | C97: ='Effort - Website'!G79 -> 13 | D97: 1 | E97: =ROUND(C97*D97,0) -> 13
A98: Q1 | B98: NIC / MeitY hosting provisioning, IaC, environments | C98: ='Effort - Website'!G83 -> 31 | D98: 1 | E98: =ROUND(C98*D98,0) -> 31
A99: Q2 | B99: DR site, replication, failover, drill runbooks | C99: ='Effort - Website'!G84 -> 27 | D99: 1 | E99: =ROUND(C99*D99,0) -> 27
A100: Q3 | B100: Monitoring, IDPS, alerting, SOC handover | C100: ='Effort - Website'!G85 -> 19 | D100: 0.45 | E100: =ROUND(C100*D100,0) -> 9 | F100: Product carries monitoring; NIC-specific work remains.
A101: Q4 | B101: Security engineering and two VAPT cycles | C101: ='Effort - Website'!G86 -> 31 | D101: 1 | E101: =ROUND(C101*D101,0) -> 31
...

Sheet Independent Estimate
A1: Second Method — COCOMO II Post-Architecture
A2: Genuinely independent of the module breakdown. Size comes from counted artefacts; every coefficient is Boehm's published calibration, not a rate chosen to agree.
B4: WHY THIS REPLACES THE TRIANGULATION SHEET
B5: The problem | C5: The previous sheet used a per-obligation rate and a per-screen rate that were within 3% and 10% of the values needed to reproduce the bottom-up answer. They were calibrated to agree, so the convergence corroborated nothing. It has been deleted rather than patched.
B6: The replacement | C6: Function-point sizing from counted artefacts, backfired to source lines, then Boehm's COCOMO II effort equation. Nothing in this chain reads the module estimates, so it is free to disagree — and it does.
B8: STEP 1 — FUNCTION POINT COUNT
B9: Component | C9: Count (items) | D9: FP weight (dimensionless) | E9: Points (unadjusted FP)
B10: Internal logical files (data entities) | C10: 30 | D10: 12 | E10: =C10*D10 -> 360
B11: External interface files (integrations) | C11: 13 | D11: 7 | E11: =C11*D11 -> 91
B12: External inputs (forms and actions) | C12: 55 | D12: 4 | E12: =C12*D12 -> 220
B13: External outputs (documents, reports, dashboards) | C13: 35 | D13: 5 | E13: =C13*D13 -> 175
B14: External inquiries (searches and lookups) | C14: 25 | D14: 4 | E14: =C14*D14 -> 100
B15: Unadjusted function points | E15: =SUM(E10:E14) -> 946
B16: Value adjustment factor | E16: 1.19 | F16: 0.65 + 0.01 x 54 across the 14 general system characteristics.
B17: Adjusted function points | E17: =ROUND(E15*E16,0) -> 1126
B18: Source lines per function point | E18: 46 | F18: Typical backfire ratio for a modern web and services stack.
B19: Size (KSLOC) | E19: =ROUND(E17*E18/1000,1) -> 51.8
B21: STEP 2 — COCOMO II PARAMETERS
B22: Scale factors | C22: Rating | D22: Value
B23: PREC precedentedness | C23: Nominal | D23: 3.72
B24: FLEX development flexibility | C24: Low | D24: 4.05
B25: RESL risk resolution | C25: Low | D25: 5.65
B26: TEAM cohesion | C26: Nominal | D26: 3.29
B27: PMAT process maturity | C27: High | D27: 3.12
B28: Sum of scale factors | D28: =SUM(D23:D27) -> 19.83
B29: Exponent E = 0.91 + 0.01 x SF | D29: =0.91+0.01*D28 -> 1.1083
B30: Product of the 17 effort multipliers | D30: 1.012 | F30: RELY, DATA, CPLX, RUSE and DOCU raise it; ACAP, PCAP, PLEX, LTEX, TOOL and SITE lower it; PCON is Low because of the 16-month attrition exposure.
B32: STEP 3 — RESULT
B33: Effort (person-months) = 2.94 x KSLOC^E x EM | D33: =ROUND(2.94*E19^D29*D30,0) -> 236
B34: Person-days per person-month | D34: 19
B35: Software construction effort | D35: =ROUND(D33*D34,0) -> 4484
B36: Plus inception and requirements at 7% | D36: =ROUND(D35*0.07,0) -> 314
B37: Plus non-code workstreams from the bottom-up | D37: 284 | F37: Content and catalogue migration, hosting, certification and training. COCOMO sizes code, not these.
B38: COCOMO II LIKE-FOR-LIKE TOTAL | D38: =D35+D36+D37 -> 5082
B40: Bottom-up P50 (simulation) | D40: 3426
B41: Divergence | D41: =IFERROR((D38-D40)/D40,0) -> 0.48336252 | F41: A real second opinion is allowed to disagree. Read the note below before deciding which to trust.
B43: How to read the gap | C43: If COCOMO reads high, the likely causes are that the backfire ratio overstates a configuration-heavy build (much of this system is CMS and commerce configuration, not bespoke code) and that the function-point count treats configured features as if they were written from scratch. If COCOMO reads low, the bottom-up is probably carrying coordination and governance overhead that the parametric model prices more cheaply. Either way the two should be reconciled explicitly before a bid, and the honest position is that a single-method estimate was never safe.
B45: RECONCILIATION — what would make the two methods agree?
B46: Backfire ratio at which COCOMO equals the bottom-up | D46: 31.4 | F46: Against the 46 used above. The whole 48% divergence rests on this one input.
B48: Backfire ratio (SLOC per FP) | C48: COCOMO total (PD) | D48: vs bottom-up (%) | F48: Reading
B49: 25 | C49: 2728 | D49: -0.20370176 | F49: Very high reuse; mostly configuration.
B50: 31 | C50: 3386 | D50: -0.011634577 | F50: Configuration-heavy CMS and commerce build. Reconciles the two methods.
B51: 35 | C51: 3833 | D51: 0.11872548 | F51: Mixed configuration and bespoke.
B52: 40 | C52: 4399 | D52: 0.28394512 | F52: Mostly bespoke, modern framework.
B53: 46 | C53: 5088 | D53: 0.48516784 | F53: Used above. Assumes largely bespoke code.
B54: 55 | C54: 6140 | D54: 0.79228815 | F54: Bespoke, lower-level language.
B56: Verdict | C56: The two methods are not really 48% apart on effort — they are apart on one assumption about how much of this system is written versus configured. At 31 source lines per function point they agree exactly, and 31 is a defensible ratio for a build that is largely CMS and commerce configuration. At 46, which assumes bespoke code throughout, COCOMO reads 5,086 PD. The bottom-up implicitly assumes the configuration-heavy world. That assumption should be stated in the bid and tested at architecture, because if the build turns out to be more bespoke than assumed, the parametric model says the exposure is roughly 1,600 person-days.

Sheet Unification Savings
A1: Unified Platform vs Two Independent Builds
A2: Each saving is now a percentage of the specific modules it reduces, computed live. The guard column flags any saving that exceeds its own source.
A4: Ref | B4: Duplicated capability | C4: Source modules | D4: Source (PD) | E4: Reduction (%) | F4: Saving (PD) | G4: Guard | H4: Rationale
A5: U1 | B5: Single identity provider and SSO | C5: E8, O6 | D5: ='Effort - Mobile & IPRS'!G56+'Effort - Website'!G72 -> 62 | E5: 0.42 | F5: =ROUND(D5*E5,0) -> 26 | G5: =IF(F5>D5,"OVER-CLAIM","ok") -> ok | H5: One IdP serves app, console and portal.
A6: U2 | B6: One catalogue and commerce core, two front ends | C6: C4, N1, N3, N4, N5, N6 | D6: ='Effort - Mobile & IPRS'!G20+'Effort - Website'!G55+'Effort - Website'!G57+'Effort - Website'!G58+'Effort - Website'!G59+'Effort - Website'!G60 -> 168 | E6: 0.62 | F6: =ROUND(D6*E6,0) -> 104 | G6: =IF(F6>D6,"OVER-CLAIM","ok") -> ok | H6: Both documents sell the same publications.
A7: U3 | B7: Single payment integration | C7: E3, N4 | D7: ='Effort - Mobile & IPRS'!G51+'Effort - Website'!G58 -> 34 | E7: 0.55 | F7: =ROUND(D7*E7,0) -> 19 | G7: =IF(F7>D7,"OVER-CLAIM","ok") -> ok | H7: One merchant account, one PCI scope.
A8: U4 | B8: Shared notification and communication service | C8: E7, D9, O5 | D8: ='Effort - Mobile & IPRS'!G55+'Effort - Mobile & IPRS'!G41+'Effort - Website'!G71 -> 65 | E8: 0.52 | F8: =ROUND(D8*E8,0) -> 34 | G8: =IF(F8>D8,"OVER-CLAIM","ok") -> ok | H8: One template store, one DLT registration.
A9: U5 | B9: Shared immutable audit-log subsystem | C9: D13, J6 | D9: ='Effort - Mobile & IPRS'!G45+'Effort - Website'!G22 -> 45 | E9: 0.55 | F9: =ROUND(D9*E9,0) -> 25 | G9: =IF(F9>D9,"OVER-CLAIM","ok") -> ok | H9: Required by both; build once.
A10: U6 | B10: Shared analytics and MIS layer | C10: D11, D12, O1, O2, O3 | D10: ='Effort - Mobile & IPRS'!G43+'Effort - Mobile & IPRS'!G44+'Effort - Website'!G67+'Effort - Website'!G68+'Effort - Website'!G69 -> 133 | E10: 0.35 | F10: =ROUND(D10*E10,0) -> 47 | G10: =IF(F10>D10,"OVER-CLAIM","ok") -> ok | H10: One MIS with role-scoped views.
A11: U7 | B11: Shared infrastructure, DR and monitoring | C11: E11, Q1, Q2, Q3 | D11: ='Effort - Mobile & IPRS'!G59+'Effort - Website'!G83+'Effort - Website'!G84+'Effort - Website'!G85 -> 123 | E11: 0.36 | F11: =ROUND(D11*E11,0) -> 44 | G11: =IF(F11>D11,"OVER-CLAIM","ok") -> ok | H11: One hosting footprint, one DR site.
A12: U8 | B12: Shared design system and accessibility | C12: B1, I1, C10, L4 | D12: ='Effort - Mobile & IPRS'!G11+'Effort - Website'!G11+'Effort - Mobile & IPRS'!G26+'Effort - Website'!G41 -> 123 | E12: 0.25 | F12: =ROUND(D12*E12,0) -> 31 | G12: =IF(F12>D12,"OVER-CLAIM","ok") -> ok | H12: One accessible library, certified once.
A13: U9 | B13: Single programme office | C13: G1, G2, S1, S2 | D13: ='Effort - Mobile & IPRS'!G74+'Effort - Mobile & IPRS'!G75+'Effort - Website'!G101+'Effort - Website'!G102 -> 252 | E13: 0.29 | F13: =ROUND(D13*E13,0) -> 73 | G13: =IF(F13>D13,"OVER-CLAIM","ok") -> ok | H13: One PMO, one change board.
A14: U10 | B14: Single certification cycle | C14: C11, E12, Q4, Q5 | D14: ='Effort - Mobile & IPRS'!G27+'Effort - Mobile & IPRS'!G60+'Effort - Website'!G86+'Effort - Website'!G87 -> 112 | E14: 0.33 | F14: =ROUND(D14*E14,0) -> 37 | G14: =IF(F14>D14,"OVER-CLAIM","ok") -> ok | H14: One CQW submission covering both surfaces.
A15: U11 | B15: Shared QA framework and automation | C15: F1, F2, F3, R1, R2, R3 | D15: ='Effort - Mobile & IPRS'!G64+'Effort - Mobile & IPRS'!G65+'Effort - Mobile & IPRS'!G66+'Effort - Website'!G91+'Effort - Website'!G92+'Effort - Website'!G93 -> 283 | E15: 0.19 | F15: =ROUND(D15*E15,0) -> 54 | G15: =IF(F15>D15,"OVER-CLAIM","ok") -> ok | H15: One automation framework and test-data factory.
A16: U12 | B16: Single data-migration pipeline | C16: N2, N9, P1, P2 | D16: ='Effort - Website'!G56+'Effort - Website'!G63+'Effort - Website'!G76+'Effort - Website'!G77 -> 123 | E16: 0.24 | F16: =ROUND(D16*E16,0) -> 30 | G16: =IF(F16>D16,"OVER-CLAIM","ok") -> ok | H16: One extraction and load toolchain.
B17: TOTAL | D17: =SUM(D5:D16) -> 1523 | F17: =SUM(F5:F16) -> 524 | G17: =IF(COUNTIF(G5:G16,"OVER-CLAIM")>0,"CHECK","ok") -> ok

Sheet Risk Register (reclassified)
A1: Risk Register — Endogenous vs Exogenous
A2: Only exogenous risks enter the simulation. Endogenous ones are already carried by the module optimistic-to-pessimistic spread, and charging them again was double counting.
A4: Ref | B4: Risk | C4: Class | D4: Probability (0–1) | E4: Marginal impact (PD) | F4: EMV (PD) | G4: Basis for the classification
A5: K1 | B5: Commerce scope not reconciled before award | C5: Exogenous | D5: 0.55 | E5: 320 | F5: 176 | G5: A scope change, not estimation variance. No module range contemplates running two order ledgers.
A6: K2 | B6: No LIMS or QC source for CoA data | C6: Exogenous | D6: 0.7 | E6: 35 | F6: 24 | G6: E9 sizes building the ingest. This is the marginal cost of a manual QC console if no source exists at all.
A7: K3 | B7: Content volume beyond the counted baseline | C7: Exogenous | D7: 0.35 | E7: 30 | F7: 10 | G7: Reduced from 55: P1/P2 pessimistic already absorbs ordinary volume swing. Marginal only.
A8: K4 | B8: NIC / MeitY onboarding lead time | C8: Exogenous | D8: 0.6 | E8: 55 | F8: 33 | G8: Schedule slip converts to extended PMO cost, which no module carries.
A9: K5 | B9: STQC or CERT-In findings needing a third cycle | C9: Exogenous | D9: 0.45 | E9: 40 | F9: 18 | G9: Reduced from 60: Q4/Q5 already budget two cycles. Marginal is the third.
A10: K6 | B10: App store rejection cycles | C10: Exogenous | D10: 0.35 | E10: 15 | F10: 5 | G10: Outside the build estimate entirely.
A11: K7 | B11: Hindi coverage incomplete at cutover | C11: Exogenous | D11: 0.4 | E11: 15 | F11: 6 | G11: Reduced from 25: P3 range covers ordinary shortfall.
A12: K8 | B12: DPDP 13 May 2027 date missed, remediation needed | C12: Exogenous | D12: 0.5 | E12: 40 | F12: 20 | G12: Statutory date, not an estimation question.
A13: K11 | B13: Cold-chain workflow required but unscoped | C13: Exogenous | D13: 0.45 | E13: 22 | F13: 10 | G13: Pure scope addition; absent from every module.
A14: K12 | B14: Tier approval revalidation | C14: Exogenous | D14: 0.3 | E14: 5 | F14: 2 | G14: Reduced from 10: D5 now explicitly covers revalidation.
A15: K13 | B15: OpenCart data migration harder than mapped | C15: Exogenous | D15: 0.65 | E15: 25 | F15: 16 | G15: Reduced from 40: N9 range covers ordinary difficulty. Marginal only.
A16: K14 | B16: Attrition and re-ramp over 16 months | C16: Exogenous | D16: 0.8 | E16: 150 | F16: 120 | G16: Modules estimate productive effort, not replacement and re-ramp. Genuinely outside.
... A19: K9 | B19: PCI scope escalates to full DSS | C19: Exogenous | D19: 0.15 | E19: 0 | F19: 0 | G19: Cost-only exposure of INR 280 lakh; carried on the cost side, not in person-days.
B20: Expected value of exogenous risk | F20: 447
B22: Note | C22: This total is shown for reference only. It is NOT added to a percentile — the simulation samples these events inside each iteration, so their effect is already in every figure on the Monte Carlo sheet. v2's register totalled 621 PD; removing the double-counted volatility risk and reducing six others to their marginal exposure brings it to 447 PD.

Sheet Sensitivity
A1: Tornado — Derived by Simulation
A2: Each variable was swung and the whole Monte Carlo re-run at 25,000 iterations. The figures below are the resulting shift in P80, not hand-entered constants.
A4: Rank | B4: Variable | C4: P80 low case (PD) | D4: P80 high case (PD) | E4: Swing (PD) | F4: What the swing means
A5: 1 | B5: Requirement volatility (module spreads +/-30%) | C5: 2891 | D5: 4538 | E5: 1646 | F5: Acceptance criteria agreed in F0 move this to the low case.
A6: 2 | B6: Unification savings realised vs not | C6: 3716 | D6: 4218 | E6: 503 | F6: The entire case for one platform instead of two.
A7: 3 | B7: Commerce scope reconciled before award | C7: 3499 | D7: 3821 | E7: 322 | F7: The largest single lever, and it is answered by a question, not by engineering.
A8: 4 | B8: AI layer scope (workstream M) | C8: 3595 | D8: 3821 | E8: 226 | F8: Seven AI features with no accuracy criteria. Fixing thresholds pre-award is worth more than any other AI decision.
A9: 5 | B9: Content and catalogue migration (P, N2, N9) | C9: 3652 | D9: 3811 | E9: 159 | F9: Narrowed in v2 by counting the estate; still material.
A10: 6 | B10: Mobile: cross-platform vs two native codebases | C10: 3714 | D10: 3849 | E10: 135 | F10: A single technology decision.
A11: 7 | B11: Attrition and re-ramp | C11: 3644 | D11: 3741 | E11: 97 | F11: Longer schedules cost more than the day rate implies.
A12: 8 | B12: Forum and engagement scope (K6, K7) | C12: 3661 | D12: 3740 | E12: 79 | F12: Deferrable to phase 2 with no impact on commerce.
A13: 9 | B13: CoA source data / LIMS availability | C13: 3692 | D13: 3736 | E13: 44 | F13: If no QC source exists a manual console must be built.
A14: 10 | B14: Certification remediation cycles | C14: 3701 | D14: 3733 | E14: 32 | F14: Two cycles are budgeted; this is the third.

Sheet Team & Rate Card
A1: Role Mix and Blended Rate
A2: Offshore India delivery.
A4: Ref | B4: Role | C4: Share of effort (%) | D4: Rate (INR / person-day) | E4: Weighted (INR/PD) | F4: Note
A5: R1 | B5: Programme Director | C5: 0.03 | D5: 32000 | E5: =C5*D5 -> 960
A6: R2 | B6: Solution Architect | C6: 0.05 | D6: 26000 | E6: =C6*D6 -> 1300
A7: R3 | B7: Tech Lead | C7: 0.08 | D7: 20000 | E7: =C7*D7 -> 1600 | F7: Two leads: platform and experience.
A8: R4 | B8: Business Analyst | C8: 0.07 | D8: 14000 | E8: =C8*D8 -> 980 | F8: Owns the 191-obligation matrix.
A9: R5 | B9: UX / UI Designer | C9: 0.07 | D9: 15000 | E9: =C9*D9 -> 1050 | F9: Includes accessibility specialist time.
A10: R6 | B10: Senior Engineer | C10: 0.22 | D10: 16000 | E10: =C10*D10 -> 3520
A11: R7 | B11: Engineer | C11: 0.26 | D11: 11000 | E11: =C11*D11 -> 2860
A12: R8 | B12: QA Lead | C12: 0.04 | D12: 15000 | E12: =C12*D12 -> 600
A13: R9 | B13: QA Engineer | C13: 0.12 | D13: 9500 | E13: =C13*D13 -> 1140
A14: R10 | B14: DevOps / SRE | C14: 0.04 | D14: 17000 | E14: =C14*D14 -> 680 | F14: NIC/MeitY provisioning, DR automation.
A15: R11 | B15: Security Engineer | C15: 0.02 | D15: 22000 | E15: =C15*D15 -> 440 | F15: GIGW, CQW and CERT-In readiness.
B16: Blended rate (mid-tier) | C16: =SUM(C5:C15) -> 1 | E16: =ROUND(SUM(E5:E15),0) -> 15130
B19: VENDOR TIER
A20: Ref | B20: Tier | C20: Multiplier (x, dimensionless) | D20: Effective rate (INR/PD) | F20: Note
A21: T1 | B21: Boutique / specialist | C21: 0.72 | D21: =ROUND($E$16*C21,0) -> 10894 | F21: Lower rate, higher certification risk.
A22: T2 | B22: Mid-tier SI | C22: 1 | D22: =ROUND($E$16*C22,0) -> 15130 | F22: Baseline for all headline numbers.
A23: T3 | B23: Tier-1 SI | C23: 1.4 | D23: =ROUND($E$16*C23,0) -> 21182 | F23: Established NIC / STQC track record.

Sheet Scenarios & Cost
A1: Scenarios, Build Cost and Unit Economics
A2: INR. Crore = 10,000,000.
A4: Ref | B4: Scenario | C4: Effort (PD) | D4: Boutique Cr | E4: Mid-tier Cr | F4: Tier-1 Cr | G4: What it is
A5: S-A | B5: Two independent builds, as documented | C5: 4220 | D5: =$C5*'Team & Rate Card'!$D$21/10000000 -> 4.597268 | E5: =$C5*'Team & Rate Card'!$D$22/10000000 -> 6.38486 | F5: =$C5*'Team & Rate Card'!$D$23/10000000 -> 8.938804 | G5: MODELLED. The same simulation run with no unification saving realised — which is what two independent builds means. Previously this was a ratio taken from a superseded sheet, and restructuring the savings sheet silently broke it so that Scenario A read the same as Scenario B.
A6: S-B | B6: Unified platform, two front ends | C6: ='Monte Carlo'!C31 -> 3714 | D6: =$C6*'Team & Rate Card'!$D$21/10000000 -> 4.0460316 | E6: =$C6*'Team & Rate Card'!$D$22/10000000 -> 5.619282 | F6: =$C6*'Team & Rate Card'!$D$23/10000000 -> 7.8669948 | G6: RECOMMENDED. One catalogue, one identity, one audit ledger.
A7: S-C | B7: Unified, phase 1 release only | C7: =ROUND('Scenario C Model'!C109*('Monte Carlo'!$C$31/'Monte Carlo'!$C$30),0) -> 2865 | D7: =$C7*'Team & Rate Card'!$D$21/10000000 -> 3.121131 | E7: =$C7*'Team & Rate Card'!$D$22/10000000 -> 4.334745 | F7: =$C7*'Team & Rate Card'!$D$23/10000000 -> 6.068643 | G7: MODELLED. Sum of the modules that ship first, scaled from P50 to the P80 bid basis.
A8: S-D | B8: Replatform the existing estate, do not rebuild | C8: =ROUND('Scenario D Model'!C107*('Monte Carlo'!$C$31/'Monte Carlo'!$C$30),0) -> 3343 | D8: =$C8*'Team & Rate Card'!$D$21/10000000 -> 3.6418642 | E8: =$C8*'Team & Rate Card'!$D$22/10000000 -> 5.057959 | F8: =$C8*'Team & Rate Card'!$D$23/10000000 -> 7.0811426 | G8: MODELLED. Module-level replatform disposition, scaled to P80. Not yet validated against the actual OpenCart install.
A9: S-E | B9: IPC adopts the product (Lotmark tenant) | C9: =ROUND('Scenario E Model'!C107*('Monte Carlo'!$C$31/'Monte Carlo'!$C$30),0) -> 2787 | D9: =$C9*'Team & Rate Card'!$D$21/10000000 -> 3.0361578 | E9: =$C9*'Team & Rate Card'!$D$22/10000000 -> 4.216731 | F9: =$C9*'Team & Rate Card'!$D$23/10000000 -> 5.9034234 | G9: NEW. Product supplies the core; IPC pays for configuration, migration, the portal layer, certification and hosting. Add the licence separately.
B11: PASS-THROUGH AND THIRD-PARTY (INR lakh)
A12: Ref | B12: Item | C12: Low (INR lakh) | D12: Base (INR lakh) | E12: High (INR lakh) | F12: Type | G12: Note
A13: P1 | B13: STQC Certified Quality Website certification | C13: 8 | D13: 12 | E13: 18 | F13: One-time | G13: 88 mandatory GIGW guidelines assessed.
A14: P2 | B14: CERT-In empanelled security audit, 2 systems x 2 cycles | C14: 12 | D14: 18 | E14: 28 | F14: One-time
A15: P3 | B15: Hosting: NIC/MeitY primary plus DR (36 months) | C15: 45 | D15: 72 | E15: 110 | F15: Recurring | G15: 99.9% SLA, RTO 4h, RPO 15min.
A16: P4 | B16: Video streaming platform (36 months) | C16: 15 | D16: 24 | E16: 40 | F16: Recurring | G16: Required by Doc B; platform not named.
A17: P5 | B17: Payment gateway setup and annual | C17: 3 | D17: 6 | E17: 10 | F17: Recurring | G17: Excludes TDR.
A18: P6 | B18: SMS / DLT and transactional email (36 months) | C18: 8 | D18: 14 | E18: 24 | F18: Recurring
A19: P7 | B19: AI inference, vector store, moderation (36 months) | C19: 20 | D19: 38 | E19: 70 | F19: Recurring | G19: Seven AI features.
A20: P8 | B20: APM, logging, WAF, CDN (36 months) | C20: 12 | D20: 20 | E20: 34 | F20: Recurring | G20: Needed to evidence the SLA.
A21: P9 | B21: Developer accounts, code signing, TLS | C21: 1 | D21: 2 | E21: 4 | F21: One-time | G21: Store accounts must be owned by IPC.
A22: P10 | B22: Hindi coverage completion | C22: 8 | D22: 14 | E22: 26 | F22: One-time | G22: REDUCED: a Hindi site already exists.
A23: P11 | B23: Third-party accessibility audit, two cycles | C23: 5 | D23: 8 | E23: 14 | F23: One-time
A24: P12 | B24: Load-test tooling and device farm | C24: 4 | D24: 7 | E24: 12 | F24: One-time
A25: P13 | B25: DPDP Consent Manager registration and integration | C25: 4 | D25: 8 | E25: 15 | F25: Recurring | G25: NEW: Consent Manager registration opened 13 Nov 2026.
B26: Pass-through total | C26: =SUM(C13:C25) -> 145 | D26: =SUM(D13:D25) -> 243 | E26: =SUM(E13:E25) -> 405
B27: of which one-time | D27: =SUMIFS(D13:D25,$F$13:$F$25,"One-time") -> 61
B28: of which recurring over 36 months | D28: =SUMIFS(D13:D25,$F$13:$F$25,"Recurring") -> 182
B29: Annual run-rate | D29: =D28/3 -> 60.666667
B31: FIVE-YEAR TCO — SCENARIO B, MID-TIER (INR crore)
B32: AMC as % of build per annum | C32: 0.16 | D32: L1-L3 support, patching, CERT-In advisories, minor enhancements.
A34: Ref | B34: Cost line | C34: Year 0 (INR Cr) | D34: Year 1 (INR Cr) | E34: Year 2 (INR Cr) | F34: Year 3 (INR Cr) | G34: Years 4-5 (INR Cr)
A35: T1 | B35: Build effort | C35: =E6 -> 5.619282
A36: T2 | B36: One-time pass-through | C36: =D27/100 -> 0.61
A37: T3 | B37: Hosting, licences, AI run-rate | D37: =$D$29/100 -> 0.60666667 | E37: =$D$29/100 -> 0.60666667 | F37: =$D$29/100 -> 0.60666667 | G37: =2*$D$29/100 -> 1.2133333
A38: T4 | B38: AMC and application support | D38: =$E$6*$C$32 -> 0.89908512 | E38: =$E$6*$C$32 -> 0.89908512 | F38: =$E$6*$C$32 -> 0.89908512 | G38: =2*$E$6*$C$32 -> 1.7981702
B39: Total by period | C39: =SUM(C35:C38) -> 6.229282 | D39: =SUM(D35:D38) -> 1.5057518 | E39: =SUM(E35:E38) -> 1.5057518 | F39: =SUM(F35:F38) -> 1.5057518 | G39: =SUM(G35:G38) -> 3.0115036
B40: FIVE-YEAR TCO | C40: =SUM(C39:G39) -> 13.758041
B42: UNIT ECONOMICS — the number an evaluation committee computes first
B43: IPRS SKUs in catalogue | C43: 702 | D43: Counted from the published list, 24/06/2026.
B44: IMPRS SKUs in catalogue | C44: 639 | D44: Counted from the published list, 24/06/2026.
B45: Orders per year — BANDED, still unverified | C45: 9000 | D45: Replaced a single point guess with the band below. IPC can settle this from the existing OpenCart order table in minutes; until then, quote the range, never the point.
B46: Estimated monthly visitors — RETRACTED, UNVERIFIED | C46: 0 | D46: RETRACTED 18 Aug 2026. The earlier 88,000 was derived by dividing the gap between two visitor-counter readings (4,561,263 and 4,570,022) by three days — but those three days came from the pages' own Last-Modified dates, not from the read times. Both pages were fetched minutes apart, so the two readings cannot both be live and the inference is void. Cumulative average since about 2017 suggests nearer 42,000/month, which would make Doc B's 100,000 a growth allowance rather than current traffic — the opposite of what was claimed. REPLACE with IPC's analytics export or server logs before using any traffic-derived argument.
B47: Five-year cost per order | C47: =IFERROR(C40*10000000/(C45*5),0) -> 3057.3424 | D47: INR per order across five years. Compare against average order value before defending this programme on efficiency grounds.
B48: Five-year cost per catalogue SKU maintained | C48: =IFERROR(C40*10000000/(C43+C44),0) -> 102595.38 | D48: CORRECTED 18 Aug 2026. The previous formula divided by C42+C43, where C42 is a blank section header — so the denominator was 702 (IPRS only) instead of 1,341. The published figure of INR 1.92 lakh was overstated by 91%.
B51: ORDER-VOLUME SENSITIVITY (replaces the point assumption)
B52: Scenario | C52: Orders per year (count) | D52: Orders over 5 years (count) | E52: Cost per order (INR)
B53: Low — current shop is lightly used | C53: 4000 | D53: =C53*5 -> 20000 | E53: =IFERROR($C$40*10000000/D53,0) -> 6879.0205
B54: Base — planning assumption | C54: 9000 | D54: =C54*5 -> 45000 | E54: =IFERROR($C$40*10000000/D54,0) -> 3057.3424
B55: High — mobile app materially lifts demand | C55: 18000 | D55: =C55*5 -> 90000 | E55: =IFERROR($C$40*10000000/D55,0) -> 1528.6712
B56: Break-even at INR 1,000 per order | C56: =ROUND($C$40*10000000/1000/5,0) -> 27516 | E56: 1000 | F56: Annual order volume required for the platform to cost under INR 1,000 per order.
B58: The five-year cost per order swings by roughly four times across this band, which is why it must not be quoted from a single assumption. The cost per SKU maintained is the more stable and more honest unit for this platform.

Sheet Price & Commercials
A1: From Cost to Price
A2: v1 stopped at cost. This is the commercial wrapper.
B4: Build cost, Scenario B mid-tier (INR crore) | C4: ='Scenarios & Cost'!E6 -> 5.619282
B5: Target gross margin | C5: 0.28 | D5: Typical for Indian government fixed-price delivery.
B6: Price before tax | C6: =IFERROR(C4/(1-C5),0) -> 7.8045583
B7: GST on services | C7: 0.18 | D7: Verify the applicable rate and whether IPC can claim input credit as an autonomous body.
B8: QUOTED PRICE INCLUSIVE OF GST | C8: =C6*(1+C7) -> 9.2093788
B11: MILESTONE BILLING AND CASH FLOW
A12: Ref | B12: Milestone | C12: Month (M1–M16) | D12: Share of price (%) | E12: Value (INR Cr) | F12: Trigger / exit criterion
A13: M1 | B13: Mobilisation and signed SRS | C13: M2 | D13: 0.1 | E13: =$C$6*D13 -> 0.78045583 | F13: Requirements matrix signed by IPC.
A14: M2 | B14: Architecture and design system approved | C14: M4 | D14: 0.1 | E14: =$C$6*D14 -> 0.78045583 | F14: HLD approved; unified catalogue design agreed.
A15: M3 | B15: Core platform in integrated test | C15: M7 | D15: 0.15 | E15: =$C$6*D15 -> 1.1706838 | F15: Identity, catalogue, order and audit services demonstrable.
A16: M4 | B16: Portal feature-complete in UAT | C16: M10 | D16: 0.15 | E16: =$C$6*D16 -> 1.1706838 | F16: All CMS and commerce features in UAT.
A17: M5 | B17: Migration complete and verified | C17: M11 | D17: 0.1 | E17: =$C$6*D17 -> 0.78045583 | F17: Content and OpenCart data migrated; redirects verified.
A18: M6 | B18: Portal live with clean VAPT | C18: M12 | D18: 0.15 | E18: =$C$6*D18 -> 1.1706838 | F18: Live on NIC/MeitY; DR failover proven; CERT-In report clean.
A19: M7 | B19: STQC CQW certificate issued | C19: M13 | D19: 0.05 | E19: =$C$6*D19 -> 0.39022792 | F19: Certificate in hand.
A20: M8 | B20: Apps published to both stores | C20: M14 | D20: 0.1 | E20: =$C$6*D20 -> 0.78045583 | F20: Live on App Store and Play Store.
A21: M9 | B21: Hypercare complete and handover | C21: M16 | D21: 0.1 | E21: =$C$6*D21 -> 0.78045583 | F21: Steady-state AMC transition signed off.
B22: Total | D22: =SUM(D13:D21) -> 1 | E22: =SUM(E13:E21) -> 7.8045583
B24: Peak negative cash position (approx.) | C24: =ROUND(-'Scenarios & Cost'!E6*0.24,2) -> -1.35 | D24: Roughly 24% of build cost is carried before M3 clears. Working capital, not profit.
B26: GUARANTEES AND PENALTY EXPOSURE
A27: Ref | B27: Item | C27: Rate (%) | D27: Value (INR Cr) | F27: Note
A28: C1 | B28: Earnest money deposit | C28: 0.02 | D28: =$C$6*C28 -> 0.15609117 | F28: Refundable, but blocks working capital through evaluation.
A29: C2 | B29: Performance bank guarantee | C29: 0.1 | D29: =$C$6*C29 -> 0.78045583 | F29: Typically 10% of contract value for the full term plus claim period.
A30: C3 | B30: Liquidated damages cap | C30: 0.1 | D30: =$C$6*C30 -> 0.78045583 | F30: Usually 0.5% per week of delay, capped at 10%. This is the schedule risk in rupees.
A31: C4 | B31: Bank guarantee carrying cost per annum | C31: 0.015 | D31: =$C$6*0.1*C31 -> 0.011706837 | F31: Commission on the PBG value; a real cost, routinely forgotten in pricing.
B33: Margin after a full LD hit | C33: =IFERROR((C6-C6*0.1-'Scenarios & Cost'!E6)/C6,0) -> 0.18 | D33: If the LD cap is fully drawn, this is what is left. Test it before committing to the schedule.

Sheet Timeline
A1: Programme Timeline — Scenario B
A2: Effort curve ties to the recommended figure on the Confidence sheet.
A4: Ref | B4: Phase | C4: Start | D4: End | E4: Duration (months) | F4: M1 | G4: M2 | H4: M3 | I4: M4 | J4: M5 | K4: M6 | L4: M7 | M4: M8 | N4: M9 | O4: M10 | P4: M11 | Q4: M12 | R4: M13 | S4: M14 | T4: M15 | U4: M16 | V4: Exit criterion
A5: F0 | B5: Mobilisation, discovery, requirements | C5: M1 | D5: M2 | E5: 2 | V5: Signed SRS and 191-row matrix
A6: F1 | B6: Architecture, design system, platform foundation | C6: M2 | D6: M4 | E6: 3 | V6: Approved HLD, DPDP design baseline
A7: F2 | B7: Core platform: identity, catalogue, order, audit | C7: M3 | D7: M7 | E7: 5 | V7: Services in integrated test
A8: F3 | B8: Portal build: CMS, templates, facilities, forum | C8: M4 | D8: M10 | E8: 7 | V8: Feature-complete in UAT
A9: F4 | B9: Mobile app and admin console build | C9: M5 | D9: M12 | E9: 8 | V9: Feature-complete on internal track
A10: F5 | B10: Integrations, AI layer, MIS analytics | C10: M7 | D10: M12 | E10: 6 | V10: Integration contracts signed off
A11: F6 | B11: Content and OpenCart data migration | C11: M8 | D11: M11 | E11: 4 | V11: Migration verified, redirects live
A12: F7 | B12: QA, VAPT, GIGW conformance, STQC CQW | C12: M9 | D12: M14 | E12: 6 | V12: Clean VAPT, CQW certificate
A13: F8 | B13: UAT, pilot, government-lab onboarding | C13: M11 | D13: M14 | E13: 4 | V13: IPC sign-off on both surfaces
A14: F9 | B14: Portal go-live and cutover | C14: M12 | D14: M12 | E14: 1 | V14: Live on NIC/MeitY, DR proven
A15: F10 | B15: Store submission and app go-live | C15: M13 | D15: M14 | E15: 2 | V15: Published on both stores
A16: F11 | B16: Hypercare and transition to AMC | C16: M14 | D16: M16 | E16: 3 | V16: Steady-state handover
B19: Ramp weight (relative, dimensionless) | F19: 20 | G19: 38 | H19: 56 | I19: 71 | J19: 84 | K19: 92 | L19: 97 | M19: 99 | N19: 97 | O19: 92 | P19: 84 | Q19: 74 | R19: 56 | S19: 37 | T19: 22 | U19: 15
B20: Person-days in month | E20: =SUM(F20:U20) -> 3713 | F20: =ROUND('Monte Carlo'!$C$31*F$19/SUM($F$19:$U$19),0) -> 72 | G20: =ROUND('Monte Carlo'!$C$31*G$19/SUM($F$19:$U$19),0) -> 136 | H20: =ROUND('Monte Carlo'!$C$31*H$19/SUM($F$19:$U$19),0) -> 201 | I20: =ROUND('Monte Carlo'!$C$31*I$19/SUM($F$19:$U$19),0) -> 255 | J20: =ROUND('Monte Carlo'!$C$31*J$19/SUM($F$19:$U$19),0) -> 302 | K20: =ROUND('Monte Carlo'!$C$31*K$19/SUM($F$19:$U$19),0) -> 330 | L20: =ROUND('Monte Carlo'!$C$31*L$19/SUM($F$19:$U$19),0) -> 348 | M20: =ROUND('Monte Carlo'!$C$31*M$19/SUM($F$19:$U$19),0) -> 356 | ... U20: =ROUND('Monte Carlo'!$C$31*U$19/SUM($F$19:$U$19),0) -> 54
B21: Average FTE | F21: =ROUND(F20/21,1) -> 3.4 | G21: =ROUND(G20/21,1) -> 6.5 | H21: =ROUND(H20/21,1) -> 9.6 | I21: =ROUND(I20/21,1) -> 12.1 | J21: =ROUND(J20/21,1) -> 14.4 | K21: =ROUND(K20/21,1) -> 15.7 | L21: =ROUND(L20/21,1) -> 16.6 | M21: =ROUND(M20/21,1) -> 17 | ... U21: =ROUND(U20/21,1) -> 2.6
B23: Peak FTE | E23: =MAX(F21:U21) -> 17
B24: Average FTE | E24: =ROUND(AVERAGE(F21:U21),1) -> 11.1
B26: DPDP full-compliance date of 13 May 2027 falls inside this window on any realistic start. Design to it from F1 rather than remediating at F7.
B27: Staffed to the P80 bid basis so the schedule and the commercial figure agree. Planning to P50 and holding the difference as reserve is the alternative convention; it lowers peak FTE but requires the reserve to be governed explicitly.
